{"nodes": [{"id": "docs_privacy", "label": "Privacy", "file_type": "document", "source_file": "docs/PRIVACY.md", "source_location": null, "source_url": null, "captured_at": null, "author": null, "contributor": null}, {"id": "docs_privacy_local_first", "label": "Local-First Privacy Posture", "file_type": "concept", "source_file": "docs/PRIVACY.md", "source_location": null, "source_url": null, "captured_at": null, "author": null, "contributor": null, "rationale": "No xPST cloud service, hosted account, telemetry endpoint, or subscription backend; videos, captions, state, cookies, tokens, and config stay local; data leaves only toward user-configured platforms or optional webhooks."}, {"id": "docs_privacy_credential_storage", "label": "Credential Storage Policy", "file_type": "concept", "source_file": "docs/PRIVACY.md", "source_location": null, "source_url": null, "captured_at": null, "author": null, "contributor": null, "rationale": "OS keychain when available; otherwise local .enc files encrypted with Fernet when cryptography is present; if cryptography is removed, fallback relies on filesystem permissions and xPST logs a warning."}], "edges": [{"source": "docs_privacy", "target": "docs_privacy_local_first", "relation": "references", "confidence": "EXTRACTED", "confidence_score": 1.0, "source_file": "docs/PRIVACY.md", "source_location": null, "weight": 1.0}, {"source": "docs_privacy", "target": "docs_privacy_credential_storage", "relation": "references", "confidence": "EXTRACTED", "confidence_score": 1.0, "source_file": "docs/PRIVACY.md", "source_location": null, "weight": 1.0}, {"source": "docs_privacy_credential_storage", "target": "docs_api_credential_store", "relation": "conceptually_related_to", "confidence": "INFERRED", "confidence_score": 0.95, "source_file": "docs/PRIVACY.md", "source_location": null, "weight": 1.0}], "hyperedges": []}