{"nodes": [{"id": "scripts_verify_macos_artifact_verify_macos_artifact", "label": "verify_macos_artifact (.app structure + signing/notarization gate)", "file_type": "code", "source_file": "scripts/verify_macos_artifact.py", "source_location": "120-141", "source_url": null, "captured_at": null, "author": null, "contributor": null}, {"id": "scripts_verify_macos_artifact__macos_security_checks", "label": "_macos_security_checks (codesign verify, Developer ID, spctl assess, stapler validate; skipped off-Darwin)", "file_type": "code", "source_file": "scripts/verify_macos_artifact.py", "source_location": "50-117", "source_url": null, "captured_at": null, "author": null, "contributor": null}, {"id": "scripts_verify_macos_artifact_main", "label": "verify_macos_artifact.py main", "file_type": "code", "source_file": "scripts/verify_macos_artifact.py", "source_location": "144-165", "source_url": null, "captured_at": null, "author": null, "contributor": null}, {"id": "scripts_verify_macos_artifact_module", "label": "macOS Artifact Verifier Script", "file_type": "code", "source_file": "scripts/verify_macos_artifact.py", "source_location": null, "source_url": null, "captured_at": null, "author": null, "contributor": null}], "edges": [{"source": "scripts_verify_macos_artifact_main", "target": "scripts_verify_macos_artifact_verify_macos_artifact", "relation": "calls", "confidence": "EXTRACTED", "confidence_score": 1.0, "source_file": "scripts/verify_macos_artifact.py", "source_location": "153", "weight": 1.0}, {"source": "scripts_verify_macos_artifact_verify_macos_artifact", "target": "scripts_verify_macos_artifact__macos_security_checks", "relation": "calls", "confidence": "EXTRACTED", "confidence_score": 1.0, "source_file": "scripts/verify_macos_artifact.py", "source_location": "131", "weight": 1.0}, {"source": "scripts_verify_macos_artifact__macos_security_checks", "target": "scripts_sign_macos_main", "relation": "shares_data_with", "confidence": "INFERRED", "confidence_score": 0.95, "source_file": "scripts/verify_macos_artifact.py", "source_location": "97-113", "weight": 1.0}, {"source": "scripts_verify_macos_artifact__macos_security_checks", "target": "scripts_verify_windows_exe__authenticode_status", "relation": "semantically_similar_to", "confidence": "INFERRED", "confidence_score": 0.75, "source_file": "scripts/verify_macos_artifact.py", "source_location": "50-117", "weight": 1.0}], "hyperedges": []}