{"nodes": [{"id": "home_dev_xpst_tests_test_integration_py", "label": "test_integration.py", "file_type": "code", "source_file": "~/xPST/tests/test_integration.py", "source_location": "L1"}, {"id": "tests_test_integration_make_config", "label": "_make_config()", "file_type": "code", "source_file": "~/xPST/tests/test_integration.py", "source_location": "L28"}, {"id": "path", "label": "Path", "file_type": "code", "source_file": "~/xPST/tests/test_integration.py", "source_location": "L28"}, {"id": "tests_test_integration_make_video", "label": "_make_video()", "file_type": "code", "source_file": "~/xPST/tests/test_integration.py", "source_location": "L43"}, {"id": "str", "label": "str", "file_type": "code", "source_file": "~/xPST/tests/test_integration.py", "source_location": "L43"}, {"id": "videometadata", "label": "VideoMetadata", "file_type": "code", "source_file": "~/xPST/tests/test_integration.py", "source_location": "L43"}, {"id": "tests_test_integration_make_mock_uploader", "label": "_make_mock_uploader()", "file_type": "code", "source_file": "~/xPST/tests/test_integration.py", "source_location": "L52"}, {"id": "bool", "label": "bool", "file_type": "code", "source_file": "~/xPST/tests/test_integration.py", "source_location": "L52"}, {"id": "tests_test_integration_make_mock_source", "label": "_make_mock_source()", "file_type": "code", "source_file": "~/xPST/tests/test_integration.py", "source_location": "L83"}, {"id": "tests_test_integration_setup_engine_with_platforms", "label": "_setup_engine_with_platforms()", "file_type": "code", "source_file": "~/xPST/tests/test_integration.py", "source_location": "L91"}, {"id": "tests_test_integration_testfullpipelinetiktoktoall", "label": "TestFullPipelineTikTokToAll", "file_type": "code", "source_file": "~/xPST/tests/test_integration.py", "source_location": "L114"}, {"id": "tests_test_integration_testfullpipelinetiktoktoall_test_full_pipeline_tiktok_to_all", "label": ".test_full_pipeline_tiktok_to_all()", "file_type": "code", "source_file": "~/xPST/tests/test_integration.py", "source_location": "L118"}, {"id": "tests_test_integration_testduplicateprevention", "label": "TestDuplicatePrevention", "file_type": "code", "source_file": "~/xPST/tests/test_integration.py", "source_location": "L167"}, {"id": "tests_test_integration_testduplicateprevention_test_duplicate_prevention", "label": ".test_duplicate_prevention()", "file_type": "code", "source_file": "~/xPST/tests/test_integration.py", "source_location": "L171"}, {"id": "tests_test_integration_testcircuitbreaker", "label": "TestCircuitBreaker", "file_type": "code", "source_file": "~/xPST/tests/test_integration.py", "source_location": "L223"}, {"id": "tests_test_integration_testcircuitbreaker_test_circuit_breaker_opens_after_failures", "label": ".test_circuit_breaker_opens_after_failures()", "file_type": "code", "source_file": "~/xPST/tests/test_integration.py", "source_location": "L227"}, {"id": "tests_test_integration_testratelimitenforcement", "label": "TestRateLimitEnforcement", "file_type": "code", "source_file": "~/xPST/tests/test_integration.py", "source_location": "L274"}, {"id": "tests_test_integration_testratelimitenforcement_test_rate_limit_enforcement", "label": ".test_rate_limit_enforcement()", "file_type": "code", "source_file": "~/xPST/tests/test_integration.py", "source_location": "L277"}, {"id": "tests_test_integration_testratelimitenforcement_test_rate_limit_other_platforms_unaffected", "label": ".test_rate_limit_other_platforms_unaffected()", "file_type": "code", "source_file": "~/xPST/tests/test_integration.py", "source_location": "L296"}, {"id": "tests_test_integration_testhealthcheck", "label": "TestHealthCheck", "file_type": "code", "source_file": "~/xPST/tests/test_integration.py", "source_location": "L315"}, {"id": "tests_test_integration_testhealthcheck_test_health_check_all_platforms", "label": ".test_health_check_all_platforms()", "file_type": "code", "source_file": "~/xPST/tests/test_integration.py", "source_location": "L319"}, {"id": "tests_test_integration_testhealthcheck_test_health_check_handles_failures", "label": ".test_health_check_handles_failures()", "file_type": "code", "source_file": "~/xPST/tests/test_integration.py", "source_location": "L335"}, {"id": "tests_test_integration_rationale_1", "label": "Integration tests for xPST cross-posting pipeline.  Tests the full workflow from", "file_type": "rationale", "source_file": "~/xPST/tests/test_integration.py", "source_location": "L1"}, {"id": "tests_test_integration_rationale_29", "label": "Create a minimal XPSTConfig for integration testing.", "file_type": "rationale", "source_file": "~/xPST/tests/test_integration.py", "source_location": "L29"}, {"id": "tests_test_integration_rationale_44", "label": "Create a VideoMetadata for testing.", "file_type": "rationale", "source_file": "~/xPST/tests/test_integration.py", "source_location": "L44"}, {"id": "tests_test_integration_rationale_53", "label": "Create a mock platform uploader.      Args:         platform_name: Platform iden", "file_type": "rationale", "source_file": "~/xPST/tests/test_integration.py", "source_location": "L53"}, {"id": "tests_test_integration_rationale_84", "label": "Create a mock TikTok source with download support.", "file_type": "rationale", "source_file": "~/xPST/tests/test_integration.py", "source_location": "L84"}, {"id": "tests_test_integration_rationale_93", "label": "Build a CrossPostEngine with mock platforms injected.", "file_type": "rationale", "source_file": "~/xPST/tests/test_integration.py", "source_location": "L93"}, {"id": "tests_test_integration_rationale_115", "label": "End-to-end: one TikTok video \u2192 uploaded to YouTube, X, and Instagram.", "file_type": "rationale", "source_file": "~/xPST/tests/test_integration.py", "source_location": "L115"}, {"id": "tests_test_integration_rationale_119", "label": "Verify all 3 uploaders are called and state tracks all 3 platforms.", "file_type": "rationale", "source_file": "~/xPST/tests/test_integration.py", "source_location": "L119"}, {"id": "tests_test_integration_rationale_168", "label": "A video already in state should not be uploaded a second time.", "file_type": "rationale", "source_file": "~/xPST/tests/test_integration.py", "source_location": "L168"}, {"id": "tests_test_integration_rationale_172", "label": "Second attempt to post the same video_id is skipped.", "file_type": "rationale", "source_file": "~/xPST/tests/test_integration.py", "source_location": "L172"}, {"id": "tests_test_integration_rationale_224", "label": "After N consecutive failures the circuit breaker opens.", "file_type": "rationale", "source_file": "~/xPST/tests/test_integration.py", "source_location": "L224"}, {"id": "tests_test_integration_rationale_228", "label": "5 failed uploads \u2192 state marks circuit_breaker_open = True.", "file_type": "rationale", "source_file": "~/xPST/tests/test_integration.py", "source_location": "L228"}, {"id": "tests_test_integration_rationale_275", "label": "QuotaManager should block uploads once the daily limit is reached.", "file_type": "rationale", "source_file": "~/xPST/tests/test_integration.py", "source_location": "L275"}, {"id": "tests_test_integration_rationale_278", "label": "After hitting the daily limit, can_upload returns False.", "file_type": "rationale", "source_file": "~/xPST/tests/test_integration.py", "source_location": "L278"}, {"id": "tests_test_integration_rationale_297", "label": "Exhausting one platform's quota does not affect others.", "file_type": "rationale", "source_file": "~/xPST/tests/test_integration.py", "source_location": "L297"}, {"id": "tests_test_integration_rationale_316", "label": "engine.check_health() aggregates results from all platforms.", "file_type": "rationale", "source_file": "~/xPST/tests/test_integration.py", "source_location": "L316"}, {"id": "tests_test_integration_rationale_320", "label": "check_health returns data for all 3 platforms.", "file_type": "rationale", "source_file": "~/xPST/tests/test_integration.py", "source_location": "L320"}, {"id": "tests_test_integration_rationale_336", "label": "check_health gracefully handles a platform that throws.", "file_type": "rationale", "source_file": "~/xPST/tests/test_integration.py", "source_location": "L336"}], "edges": [{"source": "home_dev_xpst_tests_test_integration_py", "target": "pathlib", "relation": "imports_from", "context": "import", "confidence": "EXTRACTED", "source_file": "~/xPST/tests/test_integration.py", "source_location": "L15", "weight": 1.0}, {"source": "home_dev_xpst_tests_test_integration_py", "target": "unittest_mock", "relation": "imports_from", "context": "import", "confidence": "EXTRACTED", "source_file": "~/xPST/tests/test_integration.py", "source_location": "L16", "weight": 1.0}, {"source": "home_dev_xpst_tests_test_integration_py", "target": "pytest", "relation": "imports", "context": "import", "confidence": "EXTRACTED", "source_file": "~/xPST/tests/test_integration.py", "source_location": "L18", "weight": 1.0}, {"source": "home_dev_xpst_tests_test_integration_py", "target": "xpst_engine", "relation": "imports_from", "context": "import", "confidence": "EXTRACTED", "source_file": "~/xPST/tests/test_integration.py", "source_location": "L20", "weight": 1.0}, {"source": "home_dev_xpst_tests_test_integration_py", "target": "xpst_platforms_base", "relation": "imports_from", "context": "import", "confidence": "EXTRACTED", "source_file": "~/xPST/tests/test_integration.py", "source_location": "L21", "weight": 1.0}, {"source": "home_dev_xpst_tests_test_integration_py", "target": "xpst_sources_base", "relation": "imports_from", "context": "import", "confidence": "EXTRACTED", "source_file": "~/xPST/tests/test_integration.py", "source_location": "L22", "weight": 1.0}, {"source": "home_dev_xpst_tests_test_integration_py", "target": "tests_test_integration_make_config", "relation": "contains", "confidence": "EXTRACTED", "source_file": "~/xPST/tests/test_integration.py", "source_location": "L28", "weight": 1.0}, {"source": "tests_test_integration_make_config", "target": "path", "relation": "references", "context": "parameter_type", "confidence": "EXTRACTED", "source_file": "~/xPST/tests/test_integration.py", "source_location": "L28", "weight": 1.0}, {"source": "home_dev_xpst_tests_test_integration_py", "target": "tests_test_integration_make_video", "relation": "contains", "confidence": "EXTRACTED", "source_file": "~/xPST/tests/test_integration.py", "source_location": "L43", "weight": 1.0}, {"source": "tests_test_integration_make_video", "target": "str", "relation": "references", "context": "parameter_type", "confidence": "EXTRACTED", "source_file": "~/xPST/tests/test_integration.py", "source_location": "L43", "weight": 1.0}, {"source": "tests_test_integration_make_video", "target": "str", "relation": "references", "context": "parameter_type", "confidence": "EXTRACTED", "source_file": "~/xPST/tests/test_integration.py", "source_location": "L43", "weight": 1.0}, {"source": "tests_test_integration_make_video", "target": "videometadata", "relation": "references", "context": "return_type", "confidence": "EXTRACTED", "source_file": "~/xPST/tests/test_integration.py", "source_location": "L43", "weight": 1.0}, {"source": "home_dev_xpst_tests_test_integration_py", "target": "tests_test_integration_make_mock_uploader", "relation": "contains", "confidence": "EXTRACTED", "source_file": "~/xPST/tests/test_integration.py", "source_location": "L52", "weight": 1.0}, {"source": "tests_test_integration_make_mock_uploader", "target": "str", "relation": "references", "context": "parameter_type", "confidence": "EXTRACTED", "source_file": "~/xPST/tests/test_integration.py", "source_location": "L52", "weight": 1.0}, {"source": "tests_test_integration_make_mock_uploader", "target": "bool", "relation": "references", "context": "parameter_type", "confidence": "EXTRACTED", "source_file": "~/xPST/tests/test_integration.py", "source_location": "L52", "weight": 1.0}, {"source": "tests_test_integration_make_mock_uploader", "target": "bool", "relation": "references", "context": "parameter_type", "confidence": "EXTRACTED", "source_file": "~/xPST/tests/test_integration.py", "source_location": "L52", "weight": 1.0}, {"source": "home_dev_xpst_tests_test_integration_py", "target": "tests_test_integration_make_mock_source", "relation": "contains", "confidence": "EXTRACTED", "source_file": "~/xPST/tests/test_integration.py", "source_location": "L83", "weight": 1.0}, {"source": "home_dev_xpst_tests_test_integration_py", "target": "tests_test_integration_setup_engine_with_platforms", "relation": "contains", "confidence": "EXTRACTED", "source_file": "~/xPST/tests/test_integration.py", "source_location": "L91", "weight": 1.0}, {"source": "tests_test_integration_setup_engine_with_platforms", "target": "path", "relation": "references", "context": "parameter_type", "confidence": "EXTRACTED", "source_file": "~/xPST/tests/test_integration.py", "source_location": "L91", "weight": 1.0}, {"source": "tests_test_integration_setup_engine_with_platforms", "target": "bool", "relation": "references", "context": "parameter_type", "confidence": "EXTRACTED", "source_file": "~/xPST/tests/test_integration.py", "source_location": "L91", "weight": 1.0}, {"source": "tests_test_integration_setup_engine_with_platforms", "target": "bool", "relation": "references", "context": "parameter_type", "confidence": "EXTRACTED", "source_file": "~/xPST/tests/test_integration.py", "source_location": "L91", "weight": 1.0}, {"source": "tests_test_integration_setup_engine_with_platforms", "target": "bool", "relation": "references", "context": "parameter_type", "confidence": "EXTRACTED", "source_file": "~/xPST/tests/test_integration.py", "source_location": "L91", "weight": 1.0}, {"source": "home_dev_xpst_tests_test_integration_py", "target": "tests_test_integration_testfullpipelinetiktoktoall", "relation": "contains", "confidence": "EXTRACTED", "source_file": "~/xPST/tests/test_integration.py", "source_location": "L114", "weight": 1.0}, {"source": "tests_test_integration_testfullpipelinetiktoktoall", "target": "tests_test_integration_testfullpipelinetiktoktoall_test_full_pipeline_tiktok_to_all", "relation": "method", "confidence": "EXTRACTED", "source_file": "~/xPST/tests/test_integration.py", "source_location": "L118", "weight": 1.0}, {"source": "home_dev_xpst_tests_test_integration_py", "target": "tests_test_integration_testduplicateprevention", "relation": "contains", "confidence": "EXTRACTED", "source_file": "~/xPST/tests/test_integration.py", "source_location": "L167", "weight": 1.0}, {"source": "tests_test_integration_testduplicateprevention", "target": "tests_test_integration_testduplicateprevention_test_duplicate_prevention", "relation": "method", "confidence": "EXTRACTED", "source_file": "~/xPST/tests/test_integration.py", "source_location": "L171", "weight": 1.0}, {"source": "home_dev_xpst_tests_test_integration_py", "target": "tests_test_integration_testcircuitbreaker", "relation": "contains", "confidence": "EXTRACTED", "source_file": "~/xPST/tests/test_integration.py", "source_location": "L223", "weight": 1.0}, {"source": "tests_test_integration_testcircuitbreaker", "target": "tests_test_integration_testcircuitbreaker_test_circuit_breaker_opens_after_failures", "relation": "method", "confidence": "EXTRACTED", "source_file": "~/xPST/tests/test_integration.py", "source_location": "L227", "weight": 1.0}, {"source": "home_dev_xpst_tests_test_integration_py", "target": "tests_test_integration_testratelimitenforcement", "relation": "contains", "confidence": "EXTRACTED", "source_file": "~/xPST/tests/test_integration.py", "source_location": "L274", "weight": 1.0}, {"source": "tests_test_integration_testratelimitenforcement", "target": "tests_test_integration_testratelimitenforcement_test_rate_limit_enforcement", "relation": "method", "confidence": "EXTRACTED", "source_file": "~/xPST/tests/test_integration.py", "source_location": "L277", "weight": 1.0}, {"source": "tests_test_integration_testratelimitenforcement", "target": "tests_test_integration_testratelimitenforcement_test_rate_limit_other_platforms_unaffected", "relation": "method", "confidence": "EXTRACTED", "source_file": "~/xPST/tests/test_integration.py", "source_location": "L296", "weight": 1.0}, {"source": "home_dev_xpst_tests_test_integration_py", "target": "tests_test_integration_testhealthcheck", "relation": "contains", "confidence": "EXTRACTED", "source_file": "~/xPST/tests/test_integration.py", "source_location": "L315", "weight": 1.0}, {"source": "tests_test_integration_testhealthcheck", "target": "tests_test_integration_testhealthcheck_test_health_check_all_platforms", "relation": "method", "confidence": "EXTRACTED", "source_file": "~/xPST/tests/test_integration.py", "source_location": "L319", "weight": 1.0}, {"source": "tests_test_integration_testhealthcheck", "target": "tests_test_integration_testhealthcheck_test_health_check_handles_failures", "relation": "method", "confidence": "EXTRACTED", "source_file": "~/xPST/tests/test_integration.py", "source_location": "L335", "weight": 1.0}, {"source": "tests_test_integration_make_video", "target": "videometadata", "relation": "calls", "context": "call", "confidence": "EXTRACTED", "source_file": "~/xPST/tests/test_integration.py", "source_location": "L45", "weight": 1.0}, {"source": "tests_test_integration_setup_engine_with_platforms", "target": "tests_test_integration_make_config", "relation": "calls", "context": "call", "confidence": "EXTRACTED", "source_file": "~/xPST/tests/test_integration.py", "source_location": "L94", "weight": 1.0}, {"source": "tests_test_integration_setup_engine_with_platforms", "target": "path", "relation": "calls", "context": "call", "confidence": "EXTRACTED", "source_file": "~/xPST/tests/test_integration.py", "source_location": "L95", "weight": 1.0}, {"source": "tests_test_integration_setup_engine_with_platforms", "target": "tests_test_integration_make_mock_uploader", "relation": "calls", "context": "call", "confidence": "EXTRACTED", "source_file": "~/xPST/tests/test_integration.py", "source_location": "L100", "weight": 1.0}, {"source": "tests_test_integration_testfullpipelinetiktoktoall_test_full_pipeline_tiktok_to_all", "target": "tests_test_integration_setup_engine_with_platforms", "relation": "calls", "context": "call", "confidence": "EXTRACTED", "source_file": "~/xPST/tests/test_integration.py", "source_location": "L120", "weight": 1.0}, {"source": "tests_test_integration_testfullpipelinetiktoktoall_test_full_pipeline_tiktok_to_all", "target": "tests_test_integration_make_video", "relation": "calls", "context": "call", "confidence": "EXTRACTED", "source_file": "~/xPST/tests/test_integration.py", "source_location": "L121", "weight": 1.0}, {"source": "tests_test_integration_testfullpipelinetiktoktoall_test_full_pipeline_tiktok_to_all", "target": "path", "relation": "calls", "context": "call", "confidence": "EXTRACTED", "source_file": "~/xPST/tests/test_integration.py", "source_location": "L124", "weight": 1.0}, {"source": "tests_test_integration_testduplicateprevention_test_duplicate_prevention", "target": "tests_test_integration_setup_engine_with_platforms", "relation": "calls", "context": "call", "confidence": "EXTRACTED", "source_file": "~/xPST/tests/test_integration.py", "source_location": "L173", "weight": 1.0}, {"source": "tests_test_integration_testduplicateprevention_test_duplicate_prevention", "target": "tests_test_integration_make_video", "relation": "calls", "context": "call", "confidence": "EXTRACTED", "source_file": "~/xPST/tests/test_integration.py", "source_location": "L174", "weight": 1.0}, {"source": "tests_test_integration_testduplicateprevention_test_duplicate_prevention", "target": "path", "relation": "calls", "context": "call", "confidence": "EXTRACTED", "source_file": "~/xPST/tests/test_integration.py", "source_location": "L176", "weight": 1.0}, {"source": "tests_test_integration_testcircuitbreaker_test_circuit_breaker_opens_after_failures", "target": "tests_test_integration_setup_engine_with_platforms", "relation": "calls", "context": "call", "confidence": "EXTRACTED", "source_file": "~/xPST/tests/test_integration.py", "source_location": "L229", "weight": 1.0}, {"source": "tests_test_integration_testcircuitbreaker_test_circuit_breaker_opens_after_failures", "target": "path", "relation": "calls", "context": "call", "confidence": "EXTRACTED", "source_file": "~/xPST/tests/test_integration.py", "source_location": "L231", "weight": 1.0}, {"source": "tests_test_integration_testcircuitbreaker_test_circuit_breaker_opens_after_failures", "target": "tests_test_integration_make_video", "relation": "calls", "context": "call", "confidence": "EXTRACTED", "source_file": "~/xPST/tests/test_integration.py", "source_location": "L236", "weight": 1.0}, {"source": "tests_test_integration_testhealthcheck_test_health_check_all_platforms", "target": "tests_test_integration_setup_engine_with_platforms", "relation": "calls", "context": "call", "confidence": "EXTRACTED", "source_file": "~/xPST/tests/test_integration.py", "source_location": "L321", "weight": 1.0}, {"source": "tests_test_integration_testhealthcheck_test_health_check_handles_failures", "target": "tests_test_integration_setup_engine_with_platforms", "relation": "calls", "context": "call", "confidence": "EXTRACTED", "source_file": "~/xPST/tests/test_integration.py", "source_location": "L337", "weight": 1.0}, {"source": "tests_test_integration_rationale_1", "target": "home_dev_xpst_tests_test_integration_py", "relation": "rationale_for", "confidence": "EXTRACTED", "source_file": "~/xPST/tests/test_integration.py", "source_location": "L1", "weight": 1.0}, {"source": "tests_test_integration_rationale_29", "target": "tests_test_integration_make_config", "relation": "rationale_for", "confidence": "EXTRACTED", "source_file": "~/xPST/tests/test_integration.py", "source_location": "L29", "weight": 1.0}, {"source": "tests_test_integration_rationale_44", "target": "tests_test_integration_make_video", "relation": "rationale_for", "confidence": "EXTRACTED", "source_file": "~/xPST/tests/test_integration.py", "source_location": "L44", "weight": 1.0}, {"source": "tests_test_integration_rationale_53", "target": "tests_test_integration_make_mock_uploader", "relation": "rationale_for", "confidence": "EXTRACTED", "source_file": "~/xPST/tests/test_integration.py", "source_location": "L53", "weight": 1.0}, {"source": "tests_test_integration_rationale_84", "target": "tests_test_integration_make_mock_source", "relation": "rationale_for", "confidence": "EXTRACTED", "source_file": "~/xPST/tests/test_integration.py", "source_location": "L84", "weight": 1.0}, {"source": "tests_test_integration_rationale_93", "target": "tests_test_integration_setup_engine_with_platforms", "relation": "rationale_for", "confidence": "EXTRACTED", "source_file": "~/xPST/tests/test_integration.py", "source_location": "L93", "weight": 1.0}, {"source": "tests_test_integration_rationale_115", "target": "tests_test_integration_testfullpipelinetiktoktoall", "relation": "rationale_for", "confidence": "EXTRACTED", "source_file": "~/xPST/tests/test_integration.py", "source_location": "L115", "weight": 1.0}, {"source": "tests_test_integration_rationale_119", "target": "tests_test_integration_testfullpipelinetiktoktoall_test_full_pipeline_tiktok_to_all", "relation": "rationale_for", "confidence": "EXTRACTED", "source_file": "~/xPST/tests/test_integration.py", "source_location": "L119", "weight": 1.0}, {"source": "tests_test_integration_rationale_168", "target": "tests_test_integration_testduplicateprevention", "relation": "rationale_for", "confidence": "EXTRACTED", "source_file": "~/xPST/tests/test_integration.py", "source_location": "L168", "weight": 1.0}, {"source": "tests_test_integration_rationale_172", "target": "tests_test_integration_testduplicateprevention_test_duplicate_prevention", "relation": "rationale_for", "confidence": "EXTRACTED", "source_file": "~/xPST/tests/test_integration.py", "source_location": "L172", "weight": 1.0}, {"source": "tests_test_integration_rationale_224", "target": "tests_test_integration_testcircuitbreaker", "relation": "rationale_for", "confidence": "EXTRACTED", "source_file": "~/xPST/tests/test_integration.py", "source_location": "L224", "weight": 1.0}, {"source": "tests_test_integration_rationale_228", "target": "tests_test_integration_testcircuitbreaker_test_circuit_breaker_opens_after_failures", "relation": "rationale_for", "confidence": "EXTRACTED", "source_file": "~/xPST/tests/test_integration.py", "source_location": "L228", "weight": 1.0}, {"source": "tests_test_integration_rationale_275", "target": "tests_test_integration_testratelimitenforcement", "relation": "rationale_for", "confidence": "EXTRACTED", "source_file": "~/xPST/tests/test_integration.py", "source_location": "L275", "weight": 1.0}, {"source": "tests_test_integration_rationale_278", "target": "tests_test_integration_testratelimitenforcement_test_rate_limit_enforcement", "relation": "rationale_for", "confidence": "EXTRACTED", "source_file": "~/xPST/tests/test_integration.py", "source_location": "L278", "weight": 1.0}, {"source": "tests_test_integration_rationale_297", "target": "tests_test_integration_testratelimitenforcement_test_rate_limit_other_platforms_unaffected", "relation": "rationale_for", "confidence": "EXTRACTED", "source_file": "~/xPST/tests/test_integration.py", "source_location": "L297", "weight": 1.0}, {"source": "tests_test_integration_rationale_316", "target": "tests_test_integration_testhealthcheck", "relation": "rationale_for", "confidence": "EXTRACTED", "source_file": "~/xPST/tests/test_integration.py", "source_location": "L316", "weight": 1.0}, {"source": "tests_test_integration_rationale_320", "target": "tests_test_integration_testhealthcheck_test_health_check_all_platforms", "relation": "rationale_for", "confidence": "EXTRACTED", "source_file": "~/xPST/tests/test_integration.py", "source_location": "L320", "weight": 1.0}, {"source": "tests_test_integration_rationale_336", "target": "tests_test_integration_testhealthcheck_test_health_check_handles_failures", "relation": "rationale_for", "confidence": "EXTRACTED", "source_file": "~/xPST/tests/test_integration.py", "source_location": "L336", "weight": 1.0}], "raw_calls": [{"caller_nid": "tests_test_integration_make_config", "callee": "XPSTConfig", "is_member_call": false, "source_file": "~/xPST/tests/test_integration.py", "source_location": "L32"}, {"caller_nid": "tests_test_integration_make_mock_uploader", "callee": "MagicMock", "is_member_call": false, "source_file": "~/xPST/tests/test_integration.py", "source_location": "L60"}, {"caller_nid": "tests_test_integration_make_mock_uploader", "callee": "AsyncMock", "is_member_call": false, "source_file": "~/xPST/tests/test_integration.py", "source_location": "L64"}, {"caller_nid": "tests_test_integration_make_mock_uploader", "callee": "Exception", "is_member_call": false, "source_file": "~/xPST/tests/test_integration.py", "source_location": "L64"}, {"caller_nid": "tests_test_integration_make_mock_uploader", "callee": "AsyncMock", "is_member_call": false, "source_file": "~/xPST/tests/test_integration.py", "source_location": "L66"}, {"caller_nid": "tests_test_integration_make_mock_uploader", "callee": "UploadResult", "is_member_call": false, "source_file": "~/xPST/tests/test_integration.py", "source_location": "L66"}, {"caller_nid": "tests_test_integration_make_mock_uploader", "callee": "AsyncMock", "is_member_call": false, "source_file": "~/xPST/tests/test_integration.py", "source_location": "L74"}, {"caller_nid": "tests_test_integration_make_mock_uploader", "callee": "PlatformHealth", "is_member_call": false, "source_file": "~/xPST/tests/test_integration.py", "source_location": "L74"}, {"caller_nid": "tests_test_integration_make_mock_uploader", "callee": "AsyncMock", "is_member_call": false, "source_file": "~/xPST/tests/test_integration.py", "source_location": "L79"}, {"caller_nid": "tests_test_integration_make_mock_source", "callee": "MagicMock", "is_member_call": false, "source_file": "~/xPST/tests/test_integration.py", "source_location": "L85"}, {"caller_nid": "tests_test_integration_make_mock_source", "callee": "AsyncMock", "is_member_call": false, "source_file": "~/xPST/tests/test_integration.py", "source_location": "L87"}, {"caller_nid": "tests_test_integration_setup_engine_with_platforms", "callee": "mkdir", "is_member_call": true, "source_file": "~/xPST/tests/test_integration.py", "source_location": "L95"}, {"caller_nid": "tests_test_integration_setup_engine_with_platforms", "callee": "CrossPostEngine", "is_member_call": false, "source_file": "~/xPST/tests/test_integration.py", "source_location": "L97"}, {"caller_nid": "tests_test_integration_testfullpipelinetiktoktoall_test_full_pipeline_tiktok_to_all", "callee": "mkdir", "is_member_call": true, "source_file": "~/xPST/tests/test_integration.py", "source_location": "L125"}, {"caller_nid": "tests_test_integration_testfullpipelinetiktoktoall_test_full_pipeline_tiktok_to_all", "callee": "write_bytes", "is_member_call": true, "source_file": "~/xPST/tests/test_integration.py", "source_location": "L127"}, {"caller_nid": "tests_test_integration_testfullpipelinetiktoktoall_test_full_pipeline_tiktok_to_all", "callee": "object", "is_member_call": true, "source_file": "~/xPST/tests/test_integration.py", "source_location": "L130"}, {"caller_nid": "tests_test_integration_testfullpipelinetiktoktoall_test_full_pipeline_tiktok_to_all", "callee": "object", "is_member_call": true, "source_file": "~/xPST/tests/test_integration.py", "source_location": "L133"}, {"caller_nid": "tests_test_integration_testfullpipelinetiktoktoall_test_full_pipeline_tiktok_to_all", "callee": "object", "is_member_call": true, "source_file": "~/xPST/tests/test_integration.py", "source_location": "L136"}, {"caller_nid": "tests_test_integration_testfullpipelinetiktoktoall_test_full_pipeline_tiktok_to_all", "callee": "DownloadResult", "is_member_call": false, "source_file": "~/xPST/tests/test_integration.py", "source_location": "L139"}, {"caller_nid": "tests_test_integration_testfullpipelinetiktoktoall_test_full_pipeline_tiktok_to_all", "callee": "object", "is_member_call": true, "source_file": "~/xPST/tests/test_integration.py", "source_location": "L140"}, {"caller_nid": "tests_test_integration_testfullpipelinetiktoktoall_test_full_pipeline_tiktok_to_all", "callee": "check_and_post", "is_member_call": true, "source_file": "~/xPST/tests/test_integration.py", "source_location": "L144"}, {"caller_nid": "tests_test_integration_testfullpipelinetiktoktoall_test_full_pipeline_tiktok_to_all", "callee": "assert_called_once", "is_member_call": true, "source_file": "~/xPST/tests/test_integration.py", "source_location": "L154"}, {"caller_nid": "tests_test_integration_testfullpipelinetiktoktoall_test_full_pipeline_tiktok_to_all", "callee": "is_video_posted", "is_member_call": true, "source_file": "~/xPST/tests/test_integration.py", "source_location": "L160"}, {"caller_nid": "tests_test_integration_testduplicateprevention_test_duplicate_prevention", "callee": "mkdir", "is_member_call": true, "source_file": "~/xPST/tests/test_integration.py", "source_location": "L177"}, {"caller_nid": "tests_test_integration_testduplicateprevention_test_duplicate_prevention", "callee": "write_bytes", "is_member_call": true, "source_file": "~/xPST/tests/test_integration.py", "source_location": "L179"}, {"caller_nid": "tests_test_integration_testduplicateprevention_test_duplicate_prevention", "callee": "object", "is_member_call": true, "source_file": "~/xPST/tests/test_integration.py", "source_location": "L182"}, {"caller_nid": "tests_test_integration_testduplicateprevention_test_duplicate_prevention", "callee": "object", "is_member_call": true, "source_file": "~/xPST/tests/test_integration.py", "source_location": "L185"}, {"caller_nid": "tests_test_integration_testduplicateprevention_test_duplicate_prevention", "callee": "object", "is_member_call": true, "source_file": "~/xPST/tests/test_integration.py", "source_location": "L188"}, {"caller_nid": "tests_test_integration_testduplicateprevention_test_duplicate_prevention", "callee": "DownloadResult", "is_member_call": false, "source_file": "~/xPST/tests/test_integration.py", "source_location": "L191"}, {"caller_nid": "tests_test_integration_testduplicateprevention_test_duplicate_prevention", "callee": "object", "is_member_call": true, "source_file": "~/xPST/tests/test_integration.py", "source_location": "L192"}, {"caller_nid": "tests_test_integration_testduplicateprevention_test_duplicate_prevention", "callee": "check_and_post", "is_member_call": true, "source_file": "~/xPST/tests/test_integration.py", "source_location": "L196"}, {"caller_nid": "tests_test_integration_testduplicateprevention_test_duplicate_prevention", "callee": "object", "is_member_call": true, "source_file": "~/xPST/tests/test_integration.py", "source_location": "L204"}, {"caller_nid": "tests_test_integration_testduplicateprevention_test_duplicate_prevention", "callee": "check_and_post", "is_member_call": true, "source_file": "~/xPST/tests/test_integration.py", "source_location": "L209"}, {"caller_nid": "tests_test_integration_testcircuitbreaker_test_circuit_breaker_opens_after_failures", "callee": "mkdir", "is_member_call": true, "source_file": "~/xPST/tests/test_integration.py", "source_location": "L232"}, {"caller_nid": "tests_test_integration_testcircuitbreaker_test_circuit_breaker_opens_after_failures", "callee": "write_bytes", "is_member_call": true, "source_file": "~/xPST/tests/test_integration.py", "source_location": "L238"}, {"caller_nid": "tests_test_integration_testcircuitbreaker_test_circuit_breaker_opens_after_failures", "callee": "reset_mock", "is_member_call": true, "source_file": "~/xPST/tests/test_integration.py", "source_location": "L241"}, {"caller_nid": "tests_test_integration_testcircuitbreaker_test_circuit_breaker_opens_after_failures", "callee": "object", "is_member_call": true, "source_file": "~/xPST/tests/test_integration.py", "source_location": "L243"}, {"caller_nid": "tests_test_integration_testcircuitbreaker_test_circuit_breaker_opens_after_failures", "callee": "object", "is_member_call": true, "source_file": "~/xPST/tests/test_integration.py", "source_location": "L246"}, {"caller_nid": "tests_test_integration_testcircuitbreaker_test_circuit_breaker_opens_after_failures", "callee": "object", "is_member_call": true, "source_file": "~/xPST/tests/test_integration.py", "source_location": "L249"}, {"caller_nid": "tests_test_integration_testcircuitbreaker_test_circuit_breaker_opens_after_failures", "callee": "DownloadResult", "is_member_call": false, "source_file": "~/xPST/tests/test_integration.py", "source_location": "L252"}, {"caller_nid": "tests_test_integration_testcircuitbreaker_test_circuit_breaker_opens_after_failures", "callee": "object", "is_member_call": true, "source_file": "~/xPST/tests/test_integration.py", "source_location": "L253"}, {"caller_nid": "tests_test_integration_testcircuitbreaker_test_circuit_breaker_opens_after_failures", "callee": "check_and_post", "is_member_call": true, "source_file": "~/xPST/tests/test_integration.py", "source_location": "L257"}, {"caller_nid": "tests_test_integration_testcircuitbreaker_test_circuit_breaker_opens_after_failures", "callee": "get_platform_health", "is_member_call": true, "source_file": "~/xPST/tests/test_integration.py", "source_location": "L260"}, {"caller_nid": "tests_test_integration_testcircuitbreaker_test_circuit_breaker_opens_after_failures", "callee": "get", "is_member_call": true, "source_file": "~/xPST/tests/test_integration.py", "source_location": "L265"}, {"caller_nid": "tests_test_integration_testratelimitenforcement_test_rate_limit_enforcement", "callee": "QuotaManager", "is_member_call": false, "source_file": "~/xPST/tests/test_integration.py", "source_location": "L281"}, {"caller_nid": "tests_test_integration_testratelimitenforcement_test_rate_limit_enforcement", "callee": "can_upload", "is_member_call": true, "source_file": "~/xPST/tests/test_integration.py", "source_location": "L288"}, {"caller_nid": "tests_test_integration_testratelimitenforcement_test_rate_limit_enforcement", "callee": "record_upload", "is_member_call": true, "source_file": "~/xPST/tests/test_integration.py", "source_location": "L289"}, {"caller_nid": "tests_test_integration_testratelimitenforcement_test_rate_limit_enforcement", "callee": "can_upload", "is_member_call": true, "source_file": "~/xPST/tests/test_integration.py", "source_location": "L290"}, {"caller_nid": "tests_test_integration_testratelimitenforcement_test_rate_limit_enforcement", "callee": "record_upload", "is_member_call": true, "source_file": "~/xPST/tests/test_integration.py", "source_location": "L291"}, {"caller_nid": "tests_test_integration_testratelimitenforcement_test_rate_limit_enforcement", "callee": "can_upload", "is_member_call": true, "source_file": "~/xPST/tests/test_integration.py", "source_location": "L294"}, {"caller_nid": "tests_test_integration_testratelimitenforcement_test_rate_limit_other_platforms_unaffected", "callee": "QuotaManager", "is_member_call": false, "source_file": "~/xPST/tests/test_integration.py", "source_location": "L300"}, {"caller_nid": "tests_test_integration_testratelimitenforcement_test_rate_limit_other_platforms_unaffected", "callee": "record_upload", "is_member_call": true, "source_file": "~/xPST/tests/test_integration.py", "source_location": "L304"}, {"caller_nid": "tests_test_integration_testratelimitenforcement_test_rate_limit_other_platforms_unaffected", "callee": "can_upload", "is_member_call": true, "source_file": "~/xPST/tests/test_integration.py", "source_location": "L305"}, {"caller_nid": "tests_test_integration_testratelimitenforcement_test_rate_limit_other_platforms_unaffected", "callee": "can_upload", "is_member_call": true, "source_file": "~/xPST/tests/test_integration.py", "source_location": "L307"}, {"caller_nid": "tests_test_integration_testratelimitenforcement_test_rate_limit_other_platforms_unaffected", "callee": "can_upload", "is_member_call": true, "source_file": "~/xPST/tests/test_integration.py", "source_location": "L308"}, {"caller_nid": "tests_test_integration_testhealthcheck_test_health_check_all_platforms", "callee": "check_health", "is_member_call": true, "source_file": "~/xPST/tests/test_integration.py", "source_location": "L324"}, {"caller_nid": "tests_test_integration_testhealthcheck_test_health_check_handles_failures", "callee": "AsyncMock", "is_member_call": false, "source_file": "~/xPST/tests/test_integration.py", "source_location": "L340"}, {"caller_nid": "tests_test_integration_testhealthcheck_test_health_check_handles_failures", "callee": "ConnectionError", "is_member_call": false, "source_file": "~/xPST/tests/test_integration.py", "source_location": "L341"}, {"caller_nid": "tests_test_integration_testhealthcheck_test_health_check_handles_failures", "callee": "check_health", "is_member_call": true, "source_file": "~/xPST/tests/test_integration.py", "source_location": "L344"}]}