{"nodes": [{"id": "home_dev_xpst_src_xpst_state_manager_py", "label": "state_manager.py", "file_type": "code", "source_file": "~/xPST/src/xpst/state_manager.py", "source_location": "L1"}, {"id": "xpst_state_manager_statemanager", "label": "StateManager", "file_type": "code", "source_file": "~/xPST/src/xpst/state_manager.py", "source_location": "L21"}, {"id": "xpst_state_manager_statemanager_init", "label": ".__init__()", "file_type": "code", "source_file": "~/xPST/src/xpst/state_manager.py", "source_location": "L33"}, {"id": "xpstconfig", "label": "XPSTConfig", "file_type": "code", "source_file": "~/xPST/src/xpst/state_manager.py", "source_location": "L33"}, {"id": "str", "label": "str", "file_type": "code", "source_file": "~/xPST/src/xpst/state_manager.py", "source_location": "L33"}, {"id": "path", "label": "Path", "file_type": "code", "source_file": "~/xPST/src/xpst/state_manager.py", "source_location": "L33"}, {"id": "xpst_state_manager_statemanager_state_dir", "label": ".state_dir()", "file_type": "code", "source_file": "~/xPST/src/xpst/state_manager.py", "source_location": "L46"}, {"id": "xpst_state_manager_statemanager_state_file", "label": ".state_file()", "file_type": "code", "source_file": "~/xPST/src/xpst/state_manager.py", "source_location": "L51"}, {"id": "xpst_state_manager_statemanager_state", "label": "._state()", "file_type": "code", "source_file": "~/xPST/src/xpst/state_manager.py", "source_location": "L56"}, {"id": "any", "label": "Any", "file_type": "code", "source_file": "~/xPST/src/xpst/state_manager.py", "source_location": "L56"}, {"id": "xpst_state_manager_statemanager_is_posted", "label": ".is_posted()", "file_type": "code", "source_file": "~/xPST/src/xpst/state_manager.py", "source_location": "L62"}, {"id": "bool", "label": "bool", "file_type": "code", "source_file": "~/xPST/src/xpst/state_manager.py", "source_location": "L62"}, {"id": "xpst_state_manager_statemanager_is_fully_cross_posted", "label": ".is_fully_cross_posted()", "file_type": "code", "source_file": "~/xPST/src/xpst/state_manager.py", "source_location": "L69"}, {"id": "xpst_state_manager_statemanager_add_posted_video", "label": ".add_posted_video()", "file_type": "code", "source_file": "~/xPST/src/xpst/state_manager.py", "source_location": "L77"}, {"id": "xpst_state_manager_statemanager_add_posted_video_inner", "label": "._add_posted_video_inner()", "file_type": "code", "source_file": "~/xPST/src/xpst/state_manager.py", "source_location": "L91"}, {"id": "xpst_state_manager_statemanager_record_failure", "label": ".record_failure()", "file_type": "code", "source_file": "~/xPST/src/xpst/state_manager.py", "source_location": "L143"}, {"id": "xpst_state_manager_statemanager_record_failure_inner", "label": "._record_failure_inner()", "file_type": "code", "source_file": "~/xPST/src/xpst/state_manager.py", "source_location": "L152"}, {"id": "xpst_state_manager_statemanager_remove_post", "label": ".remove_post()", "file_type": "code", "source_file": "~/xPST/src/xpst/state_manager.py", "source_location": "L203"}, {"id": "xpst_state_manager_statemanager_remove_post_inner", "label": "._remove_post_inner()", "file_type": "code", "source_file": "~/xPST/src/xpst/state_manager.py", "source_location": "L207"}, {"id": "xpst_state_manager_statemanager_get_by_hash", "label": ".get_by_hash()", "file_type": "code", "source_file": "~/xPST/src/xpst/state_manager.py", "source_location": "L223"}, {"id": "xpst_state_manager_statemanager_has_hash", "label": ".has_hash()", "file_type": "code", "source_file": "~/xPST/src/xpst/state_manager.py", "source_location": "L227"}, {"id": "xpst_state_manager_statemanager_compute_hash", "label": ".compute_hash()", "file_type": "code", "source_file": "~/xPST/src/xpst/state_manager.py", "source_location": "L231"}, {"id": "xpst_state_manager_statemanager_get_dead_letter_queue", "label": ".get_dead_letter_queue()", "file_type": "code", "source_file": "~/xPST/src/xpst/state_manager.py", "source_location": "L241"}, {"id": "xpst_state_manager_statemanager_clear_dead_letter_queue", "label": ".clear_dead_letter_queue()", "file_type": "code", "source_file": "~/xPST/src/xpst/state_manager.py", "source_location": "L258"}, {"id": "int", "label": "int", "file_type": "code", "source_file": "~/xPST/src/xpst/state_manager.py", "source_location": "L258"}, {"id": "xpst_state_manager_statemanager_update_platform_health", "label": ".update_platform_health()", "file_type": "code", "source_file": "~/xPST/src/xpst/state_manager.py", "source_location": "L278"}, {"id": "xpst_state_manager_statemanager_update_last_check_time", "label": ".update_last_check_time()", "file_type": "code", "source_file": "~/xPST/src/xpst/state_manager.py", "source_location": "L312"}, {"id": "xpst_state_manager_statemanager_update_last_wake_check", "label": ".update_last_wake_check()", "file_type": "code", "source_file": "~/xPST/src/xpst/state_manager.py", "source_location": "L322"}, {"id": "xpst_state_manager_statemanager_record_circuit_breaker_failure", "label": ".record_circuit_breaker_failure()", "file_type": "code", "source_file": "~/xPST/src/xpst/state_manager.py", "source_location": "L334"}, {"id": "xpst_state_manager_statemanager_record_circuit_breaker_success", "label": ".record_circuit_breaker_success()", "file_type": "code", "source_file": "~/xPST/src/xpst/state_manager.py", "source_location": "L346"}, {"id": "xpst_state_manager_statemanager_is_circuit_breaker_open", "label": ".is_circuit_breaker_open()", "file_type": "code", "source_file": "~/xPST/src/xpst/state_manager.py", "source_location": "L361"}, {"id": "xpst_state_manager_statemanager_get_statistics", "label": ".get_statistics()", "file_type": "code", "source_file": "~/xPST/src/xpst/state_manager.py", "source_location": "L370"}, {"id": "xpst_state_manager_statemanager_save", "label": ".save()", "file_type": "code", "source_file": "~/xPST/src/xpst/state_manager.py", "source_location": "L412"}, {"id": "xpst_state_manager_statemanager_reload", "label": ".reload()", "file_type": "code", "source_file": "~/xPST/src/xpst/state_manager.py", "source_location": "L416"}, {"id": "xpst_state_manager_statemanager_get_video", "label": ".get_video()", "file_type": "code", "source_file": "~/xPST/src/xpst/state_manager.py", "source_location": "L422"}, {"id": "xpst_state_manager_statemanager_list_video_ids", "label": ".list_video_ids()", "file_type": "code", "source_file": "~/xPST/src/xpst/state_manager.py", "source_location": "L426"}, {"id": "xpst_state_manager_rationale_1", "label": "High-level state management for xPST.  Provides business logic for tracking post", "file_type": "rationale", "source_file": "~/xPST/src/xpst/state_manager.py", "source_location": "L1"}, {"id": "xpst_state_manager_rationale_22", "label": "High-level state management with business logic.      Uses StateStore for persis", "file_type": "rationale", "source_file": "~/xPST/src/xpst/state_manager.py", "source_location": "L22"}, {"id": "xpst_state_manager_rationale_34", "label": "Initialize state manager.          Args:             config: XPSTConfig instance", "file_type": "rationale", "source_file": "~/xPST/src/xpst/state_manager.py", "source_location": "L34"}, {"id": "xpst_state_manager_rationale_47", "label": "Directory containing state files.", "file_type": "rationale", "source_file": "~/xPST/src/xpst/state_manager.py", "source_location": "L47"}, {"id": "xpst_state_manager_rationale_52", "label": "Path to state.json file.", "file_type": "rationale", "source_file": "~/xPST/src/xpst/state_manager.py", "source_location": "L52"}, {"id": "xpst_state_manager_rationale_57", "label": "Get raw state from store.", "file_type": "rationale", "source_file": "~/xPST/src/xpst/state_manager.py", "source_location": "L57"}, {"id": "xpst_state_manager_rationale_63", "label": "Check if video has been posted to a platform.", "file_type": "rationale", "source_file": "~/xPST/src/xpst/state_manager.py", "source_location": "L63"}, {"id": "xpst_state_manager_rationale_70", "label": "Check if video has been posted to all target platforms.", "file_type": "rationale", "source_file": "~/xPST/src/xpst/state_manager.py", "source_location": "L70"}, {"id": "xpst_state_manager_rationale_86", "label": "Record a successfully posted video.", "file_type": "rationale", "source_file": "~/xPST/src/xpst/state_manager.py", "source_location": "L86"}, {"id": "xpst_state_manager_rationale_149", "label": "Record a failed post attempt.", "file_type": "rationale", "source_file": "~/xPST/src/xpst/state_manager.py", "source_location": "L149"}, {"id": "xpst_state_manager_rationale_204", "label": "Remove a post record from state.", "file_type": "rationale", "source_file": "~/xPST/src/xpst/state_manager.py", "source_location": "L204"}, {"id": "xpst_state_manager_rationale_224", "label": "Get video_id by content hash.", "file_type": "rationale", "source_file": "~/xPST/src/xpst/state_manager.py", "source_location": "L224"}, {"id": "xpst_state_manager_rationale_228", "label": "Check if content hash exists.", "file_type": "rationale", "source_file": "~/xPST/src/xpst/state_manager.py", "source_location": "L228"}, {"id": "xpst_state_manager_rationale_232", "label": "Compute SHA256 hash of a file.", "file_type": "rationale", "source_file": "~/xPST/src/xpst/state_manager.py", "source_location": "L232"}, {"id": "xpst_state_manager_rationale_242", "label": "Get videos that have failed on any platform.", "file_type": "rationale", "source_file": "~/xPST/src/xpst/state_manager.py", "source_location": "L242"}, {"id": "xpst_state_manager_rationale_259", "label": "Clear all dead letter queue entries.", "file_type": "rationale", "source_file": "~/xPST/src/xpst/state_manager.py", "source_location": "L259"}, {"id": "xpst_state_manager_rationale_284", "label": "Update platform health status.", "file_type": "rationale", "source_file": "~/xPST/src/xpst/state_manager.py", "source_location": "L284"}, {"id": "xpst_state_manager_rationale_313", "label": "Update the last check timestamp.", "file_type": "rationale", "source_file": "~/xPST/src/xpst/state_manager.py", "source_location": "L313"}, {"id": "xpst_state_manager_rationale_323", "label": "Update the last wake check timestamp.", "file_type": "rationale", "source_file": "~/xPST/src/xpst/state_manager.py", "source_location": "L323"}, {"id": "xpst_state_manager_rationale_335", "label": "Record a circuit breaker failure.", "file_type": "rationale", "source_file": "~/xPST/src/xpst/state_manager.py", "source_location": "L335"}, {"id": "xpst_state_manager_rationale_347", "label": "Record a circuit breaker success (reset failures).", "file_type": "rationale", "source_file": "~/xPST/src/xpst/state_manager.py", "source_location": "L347"}, {"id": "xpst_state_manager_rationale_362", "label": "Check if circuit breaker is open for a platform.", "file_type": "rationale", "source_file": "~/xPST/src/xpst/state_manager.py", "source_location": "L362"}, {"id": "xpst_state_manager_rationale_371", "label": "Get aggregate cross-posting statistics.", "file_type": "rationale", "source_file": "~/xPST/src/xpst/state_manager.py", "source_location": "L371"}, {"id": "xpst_state_manager_rationale_413", "label": "Explicitly save state to disk.", "file_type": "rationale", "source_file": "~/xPST/src/xpst/state_manager.py", "source_location": "L413"}, {"id": "xpst_state_manager_rationale_417", "label": "Reload state from disk, discarding unsaved changes.", "file_type": "rationale", "source_file": "~/xPST/src/xpst/state_manager.py", "source_location": "L417"}, {"id": "xpst_state_manager_rationale_423", "label": "Get full video record.", "file_type": "rationale", "source_file": "~/xPST/src/xpst/state_manager.py", "source_location": "L423"}, {"id": "xpst_state_manager_rationale_427", "label": "Get all tracked video IDs.", "file_type": "rationale", "source_file": "~/xPST/src/xpst/state_manager.py", "source_location": "L427"}], "edges": [{"source": "home_dev_xpst_src_xpst_state_manager_py", "target": "hashlib", "relation": "imports", "context": "import", "confidence": "EXTRACTED", "source_file": "~/xPST/src/xpst/state_manager.py", "source_location": "L9", "weight": 1.0}, {"source": "home_dev_xpst_src_xpst_state_manager_py", "target": "datetime", "relation": "imports_from", "context": "import", "confidence": "EXTRACTED", "source_file": "~/xPST/src/xpst/state_manager.py", "source_location": "L10", "weight": 1.0}, {"source": "home_dev_xpst_src_xpst_state_manager_py", "target": "pathlib", "relation": "imports_from", "context": "import", "confidence": "EXTRACTED", "source_file": "~/xPST/src/xpst/state_manager.py", "source_location": "L11", "weight": 1.0}, {"source": "home_dev_xpst_src_xpst_state_manager_py", "target": "typing", "relation": "imports_from", "context": "import", "confidence": "EXTRACTED", "source_file": "~/xPST/src/xpst/state_manager.py", "source_location": "L12", "weight": 1.0}, {"source": "home_dev_xpst_src_xpst_state_manager_py", "target": "xpst_config", "relation": "imports_from", "context": "import", "confidence": "EXTRACTED", "source_file": "~/xPST/src/xpst/state_manager.py", "source_location": "L14", "weight": 1.0}, {"source": "home_dev_xpst_src_xpst_state_manager_py", "target": "xpst_state_store", "relation": "imports_from", "context": "import", "confidence": "EXTRACTED", "source_file": "~/xPST/src/xpst/state_manager.py", "source_location": "L15", "weight": 1.0}, {"source": "home_dev_xpst_src_xpst_state_manager_py", "target": "xpst_utils_logger", "relation": "imports_from", "context": "import", "confidence": "EXTRACTED", "source_file": "~/xPST/src/xpst/state_manager.py", "source_location": "L16", "weight": 1.0}, {"source": "home_dev_xpst_src_xpst_state_manager_py", "target": "xpst_state_manager_statemanager", "relation": "contains", "confidence": "EXTRACTED", "source_file": "~/xPST/src/xpst/state_manager.py", "source_location": "L21", "weight": 1.0}, {"source": "xpst_state_manager_statemanager", "target": "xpst_state_manager_statemanager_init", "relation": "method", "confidence": "EXTRACTED", "source_file": "~/xPST/src/xpst/state_manager.py", "source_location": "L33", "weight": 1.0}, {"source": "xpst_state_manager_statemanager_init", "target": "xpstconfig", "relation": "references", "context": "parameter_type", "confidence": "EXTRACTED", "source_file": "~/xPST/src/xpst/state_manager.py", "source_location": "L33", "weight": 1.0}, {"source": "xpst_state_manager_statemanager_init", "target": "str", "relation": "references", "context": "parameter_type", "confidence": "EXTRACTED", "source_file": "~/xPST/src/xpst/state_manager.py", "source_location": "L33", "weight": 1.0}, {"source": "xpst_state_manager_statemanager_init", "target": "path", "relation": "references", "context": "parameter_type", "confidence": "EXTRACTED", "source_file": "~/xPST/src/xpst/state_manager.py", "source_location": "L33", "weight": 1.0}, {"source": "xpst_state_manager_statemanager", "target": "xpst_state_manager_statemanager_state_dir", "relation": "method", "confidence": "EXTRACTED", "source_file": "~/xPST/src/xpst/state_manager.py", "source_location": "L46", "weight": 1.0}, {"source": "xpst_state_manager_statemanager_state_dir", "target": "path", "relation": "references", "context": "return_type", "confidence": "EXTRACTED", "source_file": "~/xPST/src/xpst/state_manager.py", "source_location": "L46", "weight": 1.0}, {"source": "xpst_state_manager_statemanager", "target": "xpst_state_manager_statemanager_state_file", "relation": "method", "confidence": "EXTRACTED", "source_file": "~/xPST/src/xpst/state_manager.py", "source_location": "L51", "weight": 1.0}, {"source": "xpst_state_manager_statemanager_state_file", "target": "path", "relation": "references", "context": "return_type", "confidence": "EXTRACTED", "source_file": "~/xPST/src/xpst/state_manager.py", "source_location": "L51", "weight": 1.0}, {"source": "xpst_state_manager_statemanager", "target": "xpst_state_manager_statemanager_state", "relation": "method", "confidence": "EXTRACTED", "source_file": "~/xPST/src/xpst/state_manager.py", "source_location": "L56", "weight": 1.0}, {"source": "xpst_state_manager_statemanager_state", "target": "str", "relation": "references", "context": "generic_arg", "confidence": "EXTRACTED", "source_file": "~/xPST/src/xpst/state_manager.py", "source_location": "L56", "weight": 1.0}, {"source": "xpst_state_manager_statemanager_state", "target": "any", "relation": "references", "context": "generic_arg", "confidence": "EXTRACTED", "source_file": "~/xPST/src/xpst/state_manager.py", "source_location": "L56", "weight": 1.0}, {"source": "xpst_state_manager_statemanager", "target": "xpst_state_manager_statemanager_is_posted", "relation": "method", "confidence": "EXTRACTED", "source_file": "~/xPST/src/xpst/state_manager.py", "source_location": "L62", "weight": 1.0}, {"source": "xpst_state_manager_statemanager_is_posted", "target": "str", "relation": "references", "context": "parameter_type", "confidence": "EXTRACTED", "source_file": "~/xPST/src/xpst/state_manager.py", "source_location": "L62", "weight": 1.0}, {"source": "xpst_state_manager_statemanager_is_posted", "target": "str", "relation": "references", "context": "parameter_type", "confidence": "EXTRACTED", "source_file": "~/xPST/src/xpst/state_manager.py", "source_location": "L62", "weight": 1.0}, {"source": "xpst_state_manager_statemanager_is_posted", "target": "bool", "relation": "references", "context": "return_type", "confidence": "EXTRACTED", "source_file": "~/xPST/src/xpst/state_manager.py", "source_location": "L62", "weight": 1.0}, {"source": "xpst_state_manager_statemanager", "target": "xpst_state_manager_statemanager_is_fully_cross_posted", "relation": "method", "confidence": "EXTRACTED", "source_file": "~/xPST/src/xpst/state_manager.py", "source_location": "L69", "weight": 1.0}, {"source": "xpst_state_manager_statemanager_is_fully_cross_posted", "target": "str", "relation": "references", "context": "parameter_type", "confidence": "EXTRACTED", "source_file": "~/xPST/src/xpst/state_manager.py", "source_location": "L69", "weight": 1.0}, {"source": "xpst_state_manager_statemanager_is_fully_cross_posted", "target": "str", "relation": "references", "context": "generic_arg", "confidence": "EXTRACTED", "source_file": "~/xPST/src/xpst/state_manager.py", "source_location": "L69", "weight": 1.0}, {"source": "xpst_state_manager_statemanager_is_fully_cross_posted", "target": "bool", "relation": "references", "context": "return_type", "confidence": "EXTRACTED", "source_file": "~/xPST/src/xpst/state_manager.py", "source_location": "L69", "weight": 1.0}, {"source": "xpst_state_manager_statemanager", "target": "xpst_state_manager_statemanager_add_posted_video", "relation": "method", "confidence": "EXTRACTED", "source_file": "~/xPST/src/xpst/state_manager.py", "source_location": "L77", "weight": 1.0}, {"source": "xpst_state_manager_statemanager_add_posted_video", "target": "str", "relation": "references", "context": "parameter_type", "confidence": "EXTRACTED", "source_file": "~/xPST/src/xpst/state_manager.py", "source_location": "L77", "weight": 1.0}, {"source": "xpst_state_manager_statemanager_add_posted_video", "target": "str", "relation": "references", "context": "parameter_type", "confidence": "EXTRACTED", "source_file": "~/xPST/src/xpst/state_manager.py", "source_location": "L77", "weight": 1.0}, {"source": "xpst_state_manager_statemanager_add_posted_video", "target": "str", "relation": "references", "context": "parameter_type", "confidence": "EXTRACTED", "source_file": "~/xPST/src/xpst/state_manager.py", "source_location": "L77", "weight": 1.0}, {"source": "xpst_state_manager_statemanager_add_posted_video", "target": "str", "relation": "references", "context": "generic_arg", "confidence": "EXTRACTED", "source_file": "~/xPST/src/xpst/state_manager.py", "source_location": "L77", "weight": 1.0}, {"source": "xpst_state_manager_statemanager_add_posted_video", "target": "str", "relation": "references", "context": "generic_arg", "confidence": "EXTRACTED", "source_file": "~/xPST/src/xpst/state_manager.py", "source_location": "L77", "weight": 1.0}, {"source": "xpst_state_manager_statemanager_add_posted_video", "target": "str", "relation": "references", "context": "generic_arg", "confidence": "EXTRACTED", "source_file": "~/xPST/src/xpst/state_manager.py", "source_location": "L77", "weight": 1.0}, {"source": "xpst_state_manager_statemanager_add_posted_video", "target": "str", "relation": "references", "context": "parameter_type", "confidence": "EXTRACTED", "source_file": "~/xPST/src/xpst/state_manager.py", "source_location": "L77", "weight": 1.0}, {"source": "xpst_state_manager_statemanager_add_posted_video", "target": "str", "relation": "references", "context": "parameter_type", "confidence": "EXTRACTED", "source_file": "~/xPST/src/xpst/state_manager.py", "source_location": "L77", "weight": 1.0}, {"source": "xpst_state_manager_statemanager", "target": "xpst_state_manager_statemanager_add_posted_video_inner", "relation": "method", "confidence": "EXTRACTED", "source_file": "~/xPST/src/xpst/state_manager.py", "source_location": "L91", "weight": 1.0}, {"source": "xpst_state_manager_statemanager_add_posted_video_inner", "target": "str", "relation": "references", "context": "generic_arg", "confidence": "EXTRACTED", "source_file": "~/xPST/src/xpst/state_manager.py", "source_location": "L91", "weight": 1.0}, {"source": "xpst_state_manager_statemanager_add_posted_video_inner", "target": "any", "relation": "references", "context": "generic_arg", "confidence": "EXTRACTED", "source_file": "~/xPST/src/xpst/state_manager.py", "source_location": "L91", "weight": 1.0}, {"source": "xpst_state_manager_statemanager_add_posted_video_inner", "target": "str", "relation": "references", "context": "parameter_type", "confidence": "EXTRACTED", "source_file": "~/xPST/src/xpst/state_manager.py", "source_location": "L91", "weight": 1.0}, {"source": "xpst_state_manager_statemanager_add_posted_video_inner", "target": "str", "relation": "references", "context": "parameter_type", "confidence": "EXTRACTED", "source_file": "~/xPST/src/xpst/state_manager.py", "source_location": "L91", "weight": 1.0}, {"source": "xpst_state_manager_statemanager_add_posted_video_inner", "target": "str", "relation": "references", "context": "parameter_type", "confidence": "EXTRACTED", "source_file": "~/xPST/src/xpst/state_manager.py", "source_location": "L91", "weight": 1.0}, {"source": "xpst_state_manager_statemanager_add_posted_video_inner", "target": "str", "relation": "references", "context": "generic_arg", "confidence": "EXTRACTED", "source_file": "~/xPST/src/xpst/state_manager.py", "source_location": "L91", "weight": 1.0}, {"source": "xpst_state_manager_statemanager_add_posted_video_inner", "target": "str", "relation": "references", "context": "generic_arg", "confidence": "EXTRACTED", "source_file": "~/xPST/src/xpst/state_manager.py", "source_location": "L91", "weight": 1.0}, {"source": "xpst_state_manager_statemanager_add_posted_video_inner", "target": "str", "relation": "references", "context": "generic_arg", "confidence": "EXTRACTED", "source_file": "~/xPST/src/xpst/state_manager.py", "source_location": "L91", "weight": 1.0}, {"source": "xpst_state_manager_statemanager_add_posted_video_inner", "target": "str", "relation": "references", "context": "parameter_type", "confidence": "EXTRACTED", "source_file": "~/xPST/src/xpst/state_manager.py", "source_location": "L91", "weight": 1.0}, {"source": "xpst_state_manager_statemanager_add_posted_video_inner", "target": "str", "relation": "references", "context": "parameter_type", "confidence": "EXTRACTED", "source_file": "~/xPST/src/xpst/state_manager.py", "source_location": "L91", "weight": 1.0}, {"source": "xpst_state_manager_statemanager_add_posted_video_inner", "target": "str", "relation": "references", "context": "generic_arg", "confidence": "EXTRACTED", "source_file": "~/xPST/src/xpst/state_manager.py", "source_location": "L91", "weight": 1.0}, {"source": "xpst_state_manager_statemanager_add_posted_video_inner", "target": "any", "relation": "references", "context": "generic_arg", "confidence": "EXTRACTED", "source_file": "~/xPST/src/xpst/state_manager.py", "source_location": "L91", "weight": 1.0}, {"source": "xpst_state_manager_statemanager", "target": "xpst_state_manager_statemanager_record_failure", "relation": "method", "confidence": "EXTRACTED", "source_file": "~/xPST/src/xpst/state_manager.py", "source_location": "L143", "weight": 1.0}, {"source": "xpst_state_manager_statemanager_record_failure", "target": "str", "relation": "references", "context": "parameter_type", "confidence": "EXTRACTED", "source_file": "~/xPST/src/xpst/state_manager.py", "source_location": "L143", "weight": 1.0}, {"source": "xpst_state_manager_statemanager_record_failure", "target": "str", "relation": "references", "context": "parameter_type", "confidence": "EXTRACTED", "source_file": "~/xPST/src/xpst/state_manager.py", "source_location": "L143", "weight": 1.0}, {"source": "xpst_state_manager_statemanager_record_failure", "target": "str", "relation": "references", "context": "parameter_type", "confidence": "EXTRACTED", "source_file": "~/xPST/src/xpst/state_manager.py", "source_location": "L143", "weight": 1.0}, {"source": "xpst_state_manager_statemanager", "target": "xpst_state_manager_statemanager_record_failure_inner", "relation": "method", "confidence": "EXTRACTED", "source_file": "~/xPST/src/xpst/state_manager.py", "source_location": "L152", "weight": 1.0}, {"source": "xpst_state_manager_statemanager_record_failure_inner", "target": "str", "relation": "references", "context": "generic_arg", "confidence": "EXTRACTED", "source_file": "~/xPST/src/xpst/state_manager.py", "source_location": "L152", "weight": 1.0}, {"source": "xpst_state_manager_statemanager_record_failure_inner", "target": "any", "relation": "references", "context": "generic_arg", "confidence": "EXTRACTED", "source_file": "~/xPST/src/xpst/state_manager.py", "source_location": "L152", "weight": 1.0}, {"source": "xpst_state_manager_statemanager_record_failure_inner", "target": "str", "relation": "references", "context": "parameter_type", "confidence": "EXTRACTED", "source_file": "~/xPST/src/xpst/state_manager.py", "source_location": "L152", "weight": 1.0}, {"source": "xpst_state_manager_statemanager_record_failure_inner", "target": "str", "relation": "references", "context": "parameter_type", "confidence": "EXTRACTED", "source_file": "~/xPST/src/xpst/state_manager.py", "source_location": "L152", "weight": 1.0}, {"source": "xpst_state_manager_statemanager_record_failure_inner", "target": "str", "relation": "references", "context": "parameter_type", "confidence": "EXTRACTED", "source_file": "~/xPST/src/xpst/state_manager.py", "source_location": "L152", "weight": 1.0}, {"source": "xpst_state_manager_statemanager_record_failure_inner", "target": "str", "relation": "references", "context": "generic_arg", "confidence": "EXTRACTED", "source_file": "~/xPST/src/xpst/state_manager.py", "source_location": "L152", "weight": 1.0}, {"source": "xpst_state_manager_statemanager_record_failure_inner", "target": "any", "relation": "references", "context": "generic_arg", "confidence": "EXTRACTED", "source_file": "~/xPST/src/xpst/state_manager.py", "source_location": "L152", "weight": 1.0}, {"source": "xpst_state_manager_statemanager", "target": "xpst_state_manager_statemanager_remove_post", "relation": "method", "confidence": "EXTRACTED", "source_file": "~/xPST/src/xpst/state_manager.py", "source_location": "L203", "weight": 1.0}, {"source": "xpst_state_manager_statemanager_remove_post", "target": "str", "relation": "references", "context": "parameter_type", "confidence": "EXTRACTED", "source_file": "~/xPST/src/xpst/state_manager.py", "source_location": "L203", "weight": 1.0}, {"source": "xpst_state_manager_statemanager_remove_post", "target": "str", "relation": "references", "context": "parameter_type", "confidence": "EXTRACTED", "source_file": "~/xPST/src/xpst/state_manager.py", "source_location": "L203", "weight": 1.0}, {"source": "xpst_state_manager_statemanager", "target": "xpst_state_manager_statemanager_remove_post_inner", "relation": "method", "confidence": "EXTRACTED", "source_file": "~/xPST/src/xpst/state_manager.py", "source_location": "L207", "weight": 1.0}, {"source": "xpst_state_manager_statemanager_remove_post_inner", "target": "str", "relation": "references", "context": "generic_arg", "confidence": "EXTRACTED", "source_file": "~/xPST/src/xpst/state_manager.py", "source_location": "L207", "weight": 1.0}, {"source": "xpst_state_manager_statemanager_remove_post_inner", "target": "any", "relation": "references", "context": "generic_arg", "confidence": "EXTRACTED", "source_file": "~/xPST/src/xpst/state_manager.py", "source_location": "L207", "weight": 1.0}, {"source": "xpst_state_manager_statemanager_remove_post_inner", "target": "str", "relation": "references", "context": "parameter_type", "confidence": "EXTRACTED", "source_file": "~/xPST/src/xpst/state_manager.py", "source_location": "L207", "weight": 1.0}, {"source": "xpst_state_manager_statemanager_remove_post_inner", "target": "str", "relation": "references", "context": "parameter_type", "confidence": "EXTRACTED", "source_file": "~/xPST/src/xpst/state_manager.py", "source_location": "L207", "weight": 1.0}, {"source": "xpst_state_manager_statemanager_remove_post_inner", "target": "str", "relation": "references", "context": "generic_arg", "confidence": "EXTRACTED", "source_file": "~/xPST/src/xpst/state_manager.py", "source_location": "L207", "weight": 1.0}, {"source": "xpst_state_manager_statemanager_remove_post_inner", "target": "any", "relation": "references", "context": "generic_arg", "confidence": "EXTRACTED", "source_file": "~/xPST/src/xpst/state_manager.py", "source_location": "L207", "weight": 1.0}, {"source": "xpst_state_manager_statemanager", "target": "xpst_state_manager_statemanager_get_by_hash", "relation": "method", "confidence": "EXTRACTED", "source_file": "~/xPST/src/xpst/state_manager.py", "source_location": "L223", "weight": 1.0}, {"source": "xpst_state_manager_statemanager_get_by_hash", "target": "str", "relation": "references", "context": "parameter_type", "confidence": "EXTRACTED", "source_file": "~/xPST/src/xpst/state_manager.py", "source_location": "L223", "weight": 1.0}, {"source": "xpst_state_manager_statemanager_get_by_hash", "target": "str", "relation": "references", "context": "return_type", "confidence": "EXTRACTED", "source_file": "~/xPST/src/xpst/state_manager.py", "source_location": "L223", "weight": 1.0}, {"source": "xpst_state_manager_statemanager", "target": "xpst_state_manager_statemanager_has_hash", "relation": "method", "confidence": "EXTRACTED", "source_file": "~/xPST/src/xpst/state_manager.py", "source_location": "L227", "weight": 1.0}, {"source": "xpst_state_manager_statemanager_has_hash", "target": "str", "relation": "references", "context": "parameter_type", "confidence": "EXTRACTED", "source_file": "~/xPST/src/xpst/state_manager.py", "source_location": "L227", "weight": 1.0}, {"source": "xpst_state_manager_statemanager_has_hash", "target": "bool", "relation": "references", "context": "return_type", "confidence": "EXTRACTED", "source_file": "~/xPST/src/xpst/state_manager.py", "source_location": "L227", "weight": 1.0}, {"source": "xpst_state_manager_statemanager", "target": "xpst_state_manager_statemanager_compute_hash", "relation": "method", "confidence": "EXTRACTED", "source_file": "~/xPST/src/xpst/state_manager.py", "source_location": "L231", "weight": 1.0}, {"source": "xpst_state_manager_statemanager_compute_hash", "target": "path", "relation": "references", "context": "parameter_type", "confidence": "EXTRACTED", "source_file": "~/xPST/src/xpst/state_manager.py", "source_location": "L231", "weight": 1.0}, {"source": "xpst_state_manager_statemanager_compute_hash", "target": "str", "relation": "references", "context": "return_type", "confidence": "EXTRACTED", "source_file": "~/xPST/src/xpst/state_manager.py", "source_location": "L231", "weight": 1.0}, {"source": "xpst_state_manager_statemanager", "target": "xpst_state_manager_statemanager_get_dead_letter_queue", "relation": "method", "confidence": "EXTRACTED", "source_file": "~/xPST/src/xpst/state_manager.py", "source_location": "L241", "weight": 1.0}, {"source": "xpst_state_manager_statemanager_get_dead_letter_queue", "target": "str", "relation": "references", "context": "generic_arg", "confidence": "EXTRACTED", "source_file": "~/xPST/src/xpst/state_manager.py", "source_location": "L241", "weight": 1.0}, {"source": "xpst_state_manager_statemanager_get_dead_letter_queue", "target": "any", "relation": "references", "context": "generic_arg", "confidence": "EXTRACTED", "source_file": "~/xPST/src/xpst/state_manager.py", "source_location": "L241", "weight": 1.0}, {"source": "xpst_state_manager_statemanager", "target": "xpst_state_manager_statemanager_clear_dead_letter_queue", "relation": "method", "confidence": "EXTRACTED", "source_file": "~/xPST/src/xpst/state_manager.py", "source_location": "L258", "weight": 1.0}, {"source": "xpst_state_manager_statemanager_clear_dead_letter_queue", "target": "int", "relation": "references", "context": "return_type", "confidence": "EXTRACTED", "source_file": "~/xPST/src/xpst/state_manager.py", "source_location": "L258", "weight": 1.0}, {"source": "xpst_state_manager_statemanager", "target": "xpst_state_manager_statemanager_update_platform_health", "relation": "method", "confidence": "EXTRACTED", "source_file": "~/xPST/src/xpst/state_manager.py", "source_location": "L278", "weight": 1.0}, {"source": "xpst_state_manager_statemanager_update_platform_health", "target": "str", "relation": "references", "context": "parameter_type", "confidence": "EXTRACTED", "source_file": "~/xPST/src/xpst/state_manager.py", "source_location": "L278", "weight": 1.0}, {"source": "xpst_state_manager_statemanager_update_platform_health", "target": "str", "relation": "references", "context": "parameter_type", "confidence": "EXTRACTED", "source_file": "~/xPST/src/xpst/state_manager.py", "source_location": "L278", "weight": 1.0}, {"source": "xpst_state_manager_statemanager_update_platform_health", "target": "bool", "relation": "references", "context": "parameter_type", "confidence": "EXTRACTED", "source_file": "~/xPST/src/xpst/state_manager.py", "source_location": "L278", "weight": 1.0}, {"source": "xpst_state_manager_statemanager_update_platform_health", "target": "str", "relation": "references", "context": "parameter_type", "confidence": "EXTRACTED", "source_file": "~/xPST/src/xpst/state_manager.py", "source_location": "L278", "weight": 1.0}, {"source": "xpst_state_manager_statemanager", "target": "xpst_state_manager_statemanager_update_last_check_time", "relation": "method", "confidence": "EXTRACTED", "source_file": "~/xPST/src/xpst/state_manager.py", "source_location": "L312", "weight": 1.0}, {"source": "xpst_state_manager_statemanager", "target": "xpst_state_manager_statemanager_update_last_wake_check", "relation": "method", "confidence": "EXTRACTED", "source_file": "~/xPST/src/xpst/state_manager.py", "source_location": "L322", "weight": 1.0}, {"source": "xpst_state_manager_statemanager", "target": "xpst_state_manager_statemanager_record_circuit_breaker_failure", "relation": "method", "confidence": "EXTRACTED", "source_file": "~/xPST/src/xpst/state_manager.py", "source_location": "L334", "weight": 1.0}, {"source": "xpst_state_manager_statemanager_record_circuit_breaker_failure", "target": "str", "relation": "references", "context": "parameter_type", "confidence": "EXTRACTED", "source_file": "~/xPST/src/xpst/state_manager.py", "source_location": "L334", "weight": 1.0}, {"source": "xpst_state_manager_statemanager", "target": "xpst_state_manager_statemanager_record_circuit_breaker_success", "relation": "method", "confidence": "EXTRACTED", "source_file": "~/xPST/src/xpst/state_manager.py", "source_location": "L346", "weight": 1.0}, {"source": "xpst_state_manager_statemanager_record_circuit_breaker_success", "target": "str", "relation": "references", "context": "parameter_type", "confidence": "EXTRACTED", "source_file": "~/xPST/src/xpst/state_manager.py", "source_location": "L346", "weight": 1.0}, {"source": "xpst_state_manager_statemanager", "target": "xpst_state_manager_statemanager_is_circuit_breaker_open", "relation": "method", "confidence": "EXTRACTED", "source_file": "~/xPST/src/xpst/state_manager.py", "source_location": "L361", "weight": 1.0}, {"source": "xpst_state_manager_statemanager_is_circuit_breaker_open", "target": "str", "relation": "references", "context": "parameter_type", "confidence": "EXTRACTED", "source_file": "~/xPST/src/xpst/state_manager.py", "source_location": "L361", "weight": 1.0}, {"source": "xpst_state_manager_statemanager_is_circuit_breaker_open", "target": "bool", "relation": "references", "context": "return_type", "confidence": "EXTRACTED", "source_file": "~/xPST/src/xpst/state_manager.py", "source_location": "L361", "weight": 1.0}, {"source": "xpst_state_manager_statemanager", "target": "xpst_state_manager_statemanager_get_statistics", "relation": "method", "confidence": "EXTRACTED", "source_file": "~/xPST/src/xpst/state_manager.py", "source_location": "L370", "weight": 1.0}, {"source": "xpst_state_manager_statemanager_get_statistics", "target": "str", "relation": "references", "context": "generic_arg", "confidence": "EXTRACTED", "source_file": "~/xPST/src/xpst/state_manager.py", "source_location": "L370", "weight": 1.0}, {"source": "xpst_state_manager_statemanager_get_statistics", "target": "any", "relation": "references", "context": "generic_arg", "confidence": "EXTRACTED", "source_file": "~/xPST/src/xpst/state_manager.py", "source_location": "L370", "weight": 1.0}, {"source": "xpst_state_manager_statemanager", "target": "xpst_state_manager_statemanager_save", "relation": "method", "confidence": "EXTRACTED", "source_file": "~/xPST/src/xpst/state_manager.py", "source_location": "L412", "weight": 1.0}, {"source": "xpst_state_manager_statemanager", "target": "xpst_state_manager_statemanager_reload", "relation": "method", "confidence": "EXTRACTED", "source_file": "~/xPST/src/xpst/state_manager.py", "source_location": "L416", "weight": 1.0}, {"source": "xpst_state_manager_statemanager", "target": "xpst_state_manager_statemanager_get_video", "relation": "method", "confidence": "EXTRACTED", "source_file": "~/xPST/src/xpst/state_manager.py", "source_location": "L422", "weight": 1.0}, {"source": "xpst_state_manager_statemanager_get_video", "target": "str", "relation": "references", "context": "parameter_type", "confidence": "EXTRACTED", "source_file": "~/xPST/src/xpst/state_manager.py", "source_location": "L422", "weight": 1.0}, {"source": "xpst_state_manager_statemanager_get_video", "target": "str", "relation": "references", "context": "generic_arg", "confidence": "EXTRACTED", "source_file": "~/xPST/src/xpst/state_manager.py", "source_location": "L422", "weight": 1.0}, {"source": "xpst_state_manager_statemanager_get_video", "target": "any", "relation": "references", "context": "generic_arg", "confidence": "EXTRACTED", "source_file": "~/xPST/src/xpst/state_manager.py", "source_location": "L422", "weight": 1.0}, {"source": "xpst_state_manager_statemanager", "target": "xpst_state_manager_statemanager_list_video_ids", "relation": "method", "confidence": "EXTRACTED", "source_file": "~/xPST/src/xpst/state_manager.py", "source_location": "L426", "weight": 1.0}, {"source": "xpst_state_manager_statemanager_list_video_ids", "target": "str", "relation": "references", "context": "generic_arg", "confidence": "EXTRACTED", "source_file": "~/xPST/src/xpst/state_manager.py", "source_location": "L426", "weight": 1.0}, {"source": "xpst_state_manager_statemanager_init", "target": "path", "relation": "calls", "context": "call", "confidence": "EXTRACTED", "source_file": "~/xPST/src/xpst/state_manager.py", "source_location": "L41", "weight": 1.0}, {"source": "xpst_state_manager_statemanager_add_posted_video", "target": "xpst_state_manager_statemanager_add_posted_video_inner", "relation": "calls", "context": "call", "confidence": "EXTRACTED", "source_file": "~/xPST/src/xpst/state_manager.py", "source_location": "L87", "weight": 1.0}, {"source": "xpst_state_manager_statemanager_record_failure", "target": "xpst_state_manager_statemanager_record_failure_inner", "relation": "calls", "context": "call", "confidence": "EXTRACTED", "source_file": "~/xPST/src/xpst/state_manager.py", "source_location": "L150", "weight": 1.0}, {"source": "xpst_state_manager_statemanager_remove_post", "target": "xpst_state_manager_statemanager_remove_post_inner", "relation": "calls", "context": "call", "confidence": "EXTRACTED", "source_file": "~/xPST/src/xpst/state_manager.py", "source_location": "L205", "weight": 1.0}, {"source": "xpst_state_manager_statemanager_get_statistics", "target": "xpst_state_manager_statemanager_get_dead_letter_queue", "relation": "calls", "context": "call", "confidence": "EXTRACTED", "source_file": "~/xPST/src/xpst/state_manager.py", "source_location": "L387", "weight": 1.0}, {"source": "xpst_state_manager_rationale_1", "target": "home_dev_xpst_src_xpst_state_manager_py", "relation": "rationale_for", "confidence": "EXTRACTED", "source_file": "~/xPST/src/xpst/state_manager.py", "source_location": "L1", "weight": 1.0}, {"source": "xpst_state_manager_rationale_22", "target": "xpst_state_manager_statemanager", "relation": "rationale_for", "confidence": "EXTRACTED", "source_file": "~/xPST/src/xpst/state_manager.py", "source_location": "L22", "weight": 1.0}, {"source": "xpst_state_manager_rationale_34", "target": "xpst_state_manager_statemanager_init", "relation": "rationale_for", "confidence": "EXTRACTED", "source_file": "~/xPST/src/xpst/state_manager.py", "source_location": "L34", "weight": 1.0}, {"source": "xpst_state_manager_rationale_47", "target": "xpst_state_manager_statemanager_state_dir", "relation": "rationale_for", "confidence": "EXTRACTED", "source_file": "~/xPST/src/xpst/state_manager.py", "source_location": "L47", "weight": 1.0}, {"source": "xpst_state_manager_rationale_52", "target": "xpst_state_manager_statemanager_state_file", "relation": "rationale_for", "confidence": "EXTRACTED", "source_file": "~/xPST/src/xpst/state_manager.py", "source_location": "L52", "weight": 1.0}, {"source": "xpst_state_manager_rationale_57", "target": "xpst_state_manager_statemanager_state", "relation": "rationale_for", "confidence": "EXTRACTED", "source_file": "~/xPST/src/xpst/state_manager.py", "source_location": "L57", "weight": 1.0}, {"source": "xpst_state_manager_rationale_63", "target": "xpst_state_manager_statemanager_is_posted", "relation": "rationale_for", "confidence": "EXTRACTED", "source_file": "~/xPST/src/xpst/state_manager.py", "source_location": "L63", "weight": 1.0}, {"source": "xpst_state_manager_rationale_70", "target": "xpst_state_manager_statemanager_is_fully_cross_posted", "relation": "rationale_for", "confidence": "EXTRACTED", "source_file": "~/xPST/src/xpst/state_manager.py", "source_location": "L70", "weight": 1.0}, {"source": "xpst_state_manager_rationale_86", "target": "xpst_state_manager_statemanager_add_posted_video", "relation": "rationale_for", "confidence": "EXTRACTED", "source_file": "~/xPST/src/xpst/state_manager.py", "source_location": "L86", "weight": 1.0}, {"source": "xpst_state_manager_rationale_149", "target": "xpst_state_manager_statemanager_record_failure", "relation": "rationale_for", "confidence": "EXTRACTED", "source_file": "~/xPST/src/xpst/state_manager.py", "source_location": "L149", "weight": 1.0}, {"source": "xpst_state_manager_rationale_204", "target": "xpst_state_manager_statemanager_remove_post", "relation": "rationale_for", "confidence": "EXTRACTED", "source_file": "~/xPST/src/xpst/state_manager.py", "source_location": "L204", "weight": 1.0}, {"source": "xpst_state_manager_rationale_224", "target": "xpst_state_manager_statemanager_get_by_hash", "relation": "rationale_for", "confidence": "EXTRACTED", "source_file": "~/xPST/src/xpst/state_manager.py", "source_location": "L224", "weight": 1.0}, {"source": "xpst_state_manager_rationale_228", "target": "xpst_state_manager_statemanager_has_hash", "relation": "rationale_for", "confidence": "EXTRACTED", "source_file": "~/xPST/src/xpst/state_manager.py", "source_location": "L228", "weight": 1.0}, {"source": "xpst_state_manager_rationale_232", "target": "xpst_state_manager_statemanager_compute_hash", "relation": "rationale_for", "confidence": "EXTRACTED", "source_file": "~/xPST/src/xpst/state_manager.py", "source_location": "L232", "weight": 1.0}, {"source": "xpst_state_manager_rationale_242", "target": "xpst_state_manager_statemanager_get_dead_letter_queue", "relation": "rationale_for", "confidence": "EXTRACTED", "source_file": "~/xPST/src/xpst/state_manager.py", "source_location": "L242", "weight": 1.0}, {"source": "xpst_state_manager_rationale_259", "target": "xpst_state_manager_statemanager_clear_dead_letter_queue", "relation": "rationale_for", "confidence": "EXTRACTED", "source_file": "~/xPST/src/xpst/state_manager.py", "source_location": "L259", "weight": 1.0}, {"source": "xpst_state_manager_rationale_284", "target": "xpst_state_manager_statemanager_update_platform_health", "relation": "rationale_for", "confidence": "EXTRACTED", "source_file": "~/xPST/src/xpst/state_manager.py", "source_location": "L284", "weight": 1.0}, {"source": "xpst_state_manager_rationale_313", "target": "xpst_state_manager_statemanager_update_last_check_time", "relation": "rationale_for", "confidence": "EXTRACTED", "source_file": "~/xPST/src/xpst/state_manager.py", "source_location": "L313", "weight": 1.0}, {"source": "xpst_state_manager_rationale_323", "target": "xpst_state_manager_statemanager_update_last_wake_check", "relation": "rationale_for", "confidence": "EXTRACTED", "source_file": "~/xPST/src/xpst/state_manager.py", "source_location": "L323", "weight": 1.0}, {"source": "xpst_state_manager_rationale_335", "target": "xpst_state_manager_statemanager_record_circuit_breaker_failure", "relation": "rationale_for", "confidence": "EXTRACTED", "source_file": "~/xPST/src/xpst/state_manager.py", "source_location": "L335", "weight": 1.0}, {"source": "xpst_state_manager_rationale_347", "target": "xpst_state_manager_statemanager_record_circuit_breaker_success", "relation": "rationale_for", "confidence": "EXTRACTED", "source_file": "~/xPST/src/xpst/state_manager.py", "source_location": "L347", "weight": 1.0}, {"source": "xpst_state_manager_rationale_362", "target": "xpst_state_manager_statemanager_is_circuit_breaker_open", "relation": "rationale_for", "confidence": "EXTRACTED", "source_file": "~/xPST/src/xpst/state_manager.py", "source_location": "L362", "weight": 1.0}, {"source": "xpst_state_manager_rationale_371", "target": "xpst_state_manager_statemanager_get_statistics", "relation": "rationale_for", "confidence": "EXTRACTED", "source_file": "~/xPST/src/xpst/state_manager.py", "source_location": "L371", "weight": 1.0}, {"source": "xpst_state_manager_rationale_413", "target": "xpst_state_manager_statemanager_save", "relation": "rationale_for", "confidence": "EXTRACTED", "source_file": "~/xPST/src/xpst/state_manager.py", "source_location": "L413", "weight": 1.0}, {"source": "xpst_state_manager_rationale_417", "target": "xpst_state_manager_statemanager_reload", "relation": "rationale_for", "confidence": "EXTRACTED", "source_file": "~/xPST/src/xpst/state_manager.py", "source_location": "L417", "weight": 1.0}, {"source": "xpst_state_manager_rationale_423", "target": "xpst_state_manager_statemanager_get_video", "relation": "rationale_for", "confidence": "EXTRACTED", "source_file": "~/xPST/src/xpst/state_manager.py", "source_location": "L423", "weight": 1.0}, {"source": "xpst_state_manager_rationale_427", "target": "xpst_state_manager_statemanager_list_video_ids", "relation": "rationale_for", "confidence": "EXTRACTED", "source_file": "~/xPST/src/xpst/state_manager.py", "source_location": "L427", "weight": 1.0}], "raw_calls": [{"caller_nid": "xpst_state_manager_statemanager_init", "callee": "resolve", "is_member_call": true, "source_file": "~/xPST/src/xpst/state_manager.py", "source_location": "L41"}, {"caller_nid": "xpst_state_manager_statemanager_init", "callee": "expanduser", "is_member_call": true, "source_file": "~/xPST/src/xpst/state_manager.py", "source_location": "L41"}, {"caller_nid": "xpst_state_manager_statemanager_init", "callee": "StateStore", "is_member_call": false, "source_file": "~/xPST/src/xpst/state_manager.py", "source_location": "L42"}, {"caller_nid": "xpst_state_manager_statemanager_state", "callee": "get_raw", "is_member_call": true, "source_file": "~/xPST/src/xpst/state_manager.py", "source_location": "L58"}, {"caller_nid": "xpst_state_manager_statemanager_is_posted", "callee": "get", "is_member_call": true, "source_file": "~/xPST/src/xpst/state_manager.py", "source_location": "L64"}, {"caller_nid": "xpst_state_manager_statemanager_is_posted", "callee": "get", "is_member_call": true, "source_file": "~/xPST/src/xpst/state_manager.py", "source_location": "L67"}, {"caller_nid": "xpst_state_manager_statemanager_is_fully_cross_posted", "callee": "get", "is_member_call": true, "source_file": "~/xPST/src/xpst/state_manager.py", "source_location": "L71"}, {"caller_nid": "xpst_state_manager_statemanager_is_fully_cross_posted", "callee": "get", "is_member_call": true, "source_file": "~/xPST/src/xpst/state_manager.py", "source_location": "L74"}, {"caller_nid": "xpst_state_manager_statemanager_add_posted_video", "callee": "update", "is_member_call": true, "source_file": "~/xPST/src/xpst/state_manager.py", "source_location": "L87"}, {"caller_nid": "xpst_state_manager_statemanager_add_posted_video_inner", "callee": "isoformat", "is_member_call": true, "source_file": "~/xPST/src/xpst/state_manager.py", "source_location": "L101"}, {"caller_nid": "xpst_state_manager_statemanager_add_posted_video_inner", "callee": "utcnow", "is_member_call": true, "source_file": "~/xPST/src/xpst/state_manager.py", "source_location": "L101"}, {"caller_nid": "xpst_state_manager_statemanager_add_posted_video_inner", "callee": "items", "is_member_call": true, "source_file": "~/xPST/src/xpst/state_manager.py", "source_location": "L118"}, {"caller_nid": "xpst_state_manager_statemanager_add_posted_video_inner", "callee": "get", "is_member_call": true, "source_file": "~/xPST/src/xpst/state_manager.py", "source_location": "L120"}, {"caller_nid": "xpst_state_manager_statemanager_add_posted_video_inner", "callee": "get", "is_member_call": true, "source_file": "~/xPST/src/xpst/state_manager.py", "source_location": "L121"}, {"caller_nid": "xpst_state_manager_statemanager_add_posted_video_inner", "callee": "get", "is_member_call": true, "source_file": "~/xPST/src/xpst/state_manager.py", "source_location": "L122"}, {"caller_nid": "xpst_state_manager_statemanager_add_posted_video_inner", "callee": "get", "is_member_call": true, "source_file": "~/xPST/src/xpst/state_manager.py", "source_location": "L130"}, {"caller_nid": "xpst_state_manager_statemanager_add_posted_video_inner", "callee": "items", "is_member_call": true, "source_file": "~/xPST/src/xpst/state_manager.py", "source_location": "L133"}, {"caller_nid": "xpst_state_manager_statemanager_add_posted_video_inner", "callee": "update", "is_member_call": true, "source_file": "~/xPST/src/xpst/state_manager.py", "source_location": "L135"}, {"caller_nid": "xpst_state_manager_statemanager_add_posted_video_inner", "callee": "get", "is_member_call": true, "source_file": "~/xPST/src/xpst/state_manager.py", "source_location": "L137"}, {"caller_nid": "xpst_state_manager_statemanager_record_failure", "callee": "update", "is_member_call": true, "source_file": "~/xPST/src/xpst/state_manager.py", "source_location": "L150"}, {"caller_nid": "xpst_state_manager_statemanager_record_failure_inner", "callee": "isoformat", "is_member_call": true, "source_file": "~/xPST/src/xpst/state_manager.py", "source_location": "L159"}, {"caller_nid": "xpst_state_manager_statemanager_record_failure_inner", "callee": "utcnow", "is_member_call": true, "source_file": "~/xPST/src/xpst/state_manager.py", "source_location": "L159"}, {"caller_nid": "xpst_state_manager_statemanager_record_failure_inner", "callee": "get", "is_member_call": true, "source_file": "~/xPST/src/xpst/state_manager.py", "source_location": "L181"}, {"caller_nid": "xpst_state_manager_statemanager_record_failure_inner", "callee": "get", "is_member_call": true, "source_file": "~/xPST/src/xpst/state_manager.py", "source_location": "L181"}, {"caller_nid": "xpst_state_manager_statemanager_record_failure_inner", "callee": "get", "is_member_call": true, "source_file": "~/xPST/src/xpst/state_manager.py", "source_location": "L187"}, {"caller_nid": "xpst_state_manager_statemanager_record_failure_inner", "callee": "get", "is_member_call": true, "source_file": "~/xPST/src/xpst/state_manager.py", "source_location": "L198"}, {"caller_nid": "xpst_state_manager_statemanager_record_failure_inner", "callee": "get", "is_member_call": true, "source_file": "~/xPST/src/xpst/state_manager.py", "source_location": "L198"}, {"caller_nid": "xpst_state_manager_statemanager_remove_post", "callee": "update", "is_member_call": true, "source_file": "~/xPST/src/xpst/state_manager.py", "source_location": "L205"}, {"caller_nid": "xpst_state_manager_statemanager_remove_post_inner", "callee": "get", "is_member_call": true, "source_file": "~/xPST/src/xpst/state_manager.py", "source_location": "L209"}, {"caller_nid": "xpst_state_manager_statemanager_remove_post_inner", "callee": "get", "is_member_call": true, "source_file": "~/xPST/src/xpst/state_manager.py", "source_location": "L215"}, {"caller_nid": "xpst_state_manager_statemanager_get_by_hash", "callee": "get", "is_member_call": true, "source_file": "~/xPST/src/xpst/state_manager.py", "source_location": "L225"}, {"caller_nid": "xpst_state_manager_statemanager_compute_hash", "callee": "sha256", "is_member_call": true, "source_file": "~/xPST/src/xpst/state_manager.py", "source_location": "L233"}, {"caller_nid": "xpst_state_manager_statemanager_compute_hash", "callee": "read", "is_member_call": true, "source_file": "~/xPST/src/xpst/state_manager.py", "source_location": "L235"}, {"caller_nid": "xpst_state_manager_statemanager_compute_hash", "callee": "update", "is_member_call": true, "source_file": "~/xPST/src/xpst/state_manager.py", "source_location": "L236"}, {"caller_nid": "xpst_state_manager_statemanager_compute_hash", "callee": "hexdigest", "is_member_call": true, "source_file": "~/xPST/src/xpst/state_manager.py", "source_location": "L237"}, {"caller_nid": "xpst_state_manager_statemanager_get_dead_letter_queue", "callee": "items", "is_member_call": true, "source_file": "~/xPST/src/xpst/state_manager.py", "source_location": "L244"}, {"caller_nid": "xpst_state_manager_statemanager_get_dead_letter_queue", "callee": "get", "is_member_call": true, "source_file": "~/xPST/src/xpst/state_manager.py", "source_location": "L245"}, {"caller_nid": "xpst_state_manager_statemanager_get_dead_letter_queue", "callee": "items", "is_member_call": true, "source_file": "~/xPST/src/xpst/state_manager.py", "source_location": "L247"}, {"caller_nid": "xpst_state_manager_statemanager_get_dead_letter_queue", "callee": "append", "is_member_call": true, "source_file": "~/xPST/src/xpst/state_manager.py", "source_location": "L248"}, {"caller_nid": "xpst_state_manager_statemanager_get_dead_letter_queue", "callee": "get", "is_member_call": true, "source_file": "~/xPST/src/xpst/state_manager.py", "source_location": "L251"}, {"caller_nid": "xpst_state_manager_statemanager_get_dead_letter_queue", "callee": "get", "is_member_call": true, "source_file": "~/xPST/src/xpst/state_manager.py", "source_location": "L252"}, {"caller_nid": "xpst_state_manager_statemanager_get_dead_letter_queue", "callee": "get", "is_member_call": true, "source_file": "~/xPST/src/xpst/state_manager.py", "source_location": "L253"}, {"caller_nid": "xpst_state_manager_statemanager_get_dead_letter_queue", "callee": "get", "is_member_call": true, "source_file": "~/xPST/src/xpst/state_manager.py", "source_location": "L254"}, {"caller_nid": "xpst_state_manager_statemanager_clear_dead_letter_queue", "callee": "update", "is_member_call": true, "source_file": "~/xPST/src/xpst/state_manager.py", "source_location": "L273"}, {"caller_nid": "xpst_state_manager_statemanager_update_platform_health", "callee": "isoformat", "is_member_call": true, "source_file": "~/xPST/src/xpst/state_manager.py", "source_location": "L285"}, {"caller_nid": "xpst_state_manager_statemanager_update_platform_health", "callee": "utcnow", "is_member_call": true, "source_file": "~/xPST/src/xpst/state_manager.py", "source_location": "L285"}, {"caller_nid": "xpst_state_manager_statemanager_update_platform_health", "callee": "update", "is_member_call": true, "source_file": "~/xPST/src/xpst/state_manager.py", "source_location": "L310"}, {"caller_nid": "xpst_state_manager_statemanager_update_last_check_time", "callee": "isoformat", "is_member_call": true, "source_file": "~/xPST/src/xpst/state_manager.py", "source_location": "L314"}, {"caller_nid": "xpst_state_manager_statemanager_update_last_check_time", "callee": "utcnow", "is_member_call": true, "source_file": "~/xPST/src/xpst/state_manager.py", "source_location": "L314"}, {"caller_nid": "xpst_state_manager_statemanager_update_last_check_time", "callee": "update", "is_member_call": true, "source_file": "~/xPST/src/xpst/state_manager.py", "source_location": "L320"}, {"caller_nid": "xpst_state_manager_statemanager_update_last_wake_check", "callee": "isoformat", "is_member_call": true, "source_file": "~/xPST/src/xpst/state_manager.py", "source_location": "L324"}, {"caller_nid": "xpst_state_manager_statemanager_update_last_wake_check", "callee": "utcnow", "is_member_call": true, "source_file": "~/xPST/src/xpst/state_manager.py", "source_location": "L324"}, {"caller_nid": "xpst_state_manager_statemanager_update_last_wake_check", "callee": "update", "is_member_call": true, "source_file": "~/xPST/src/xpst/state_manager.py", "source_location": "L330"}, {"caller_nid": "xpst_state_manager_statemanager_record_circuit_breaker_failure", "callee": "update", "is_member_call": true, "source_file": "~/xPST/src/xpst/state_manager.py", "source_location": "L344"}, {"caller_nid": "xpst_state_manager_statemanager_record_circuit_breaker_success", "callee": "isoformat", "is_member_call": true, "source_file": "~/xPST/src/xpst/state_manager.py", "source_location": "L348"}, {"caller_nid": "xpst_state_manager_statemanager_record_circuit_breaker_success", "callee": "utcnow", "is_member_call": true, "source_file": "~/xPST/src/xpst/state_manager.py", "source_location": "L348"}, {"caller_nid": "xpst_state_manager_statemanager_record_circuit_breaker_success", "callee": "update", "is_member_call": true, "source_file": "~/xPST/src/xpst/state_manager.py", "source_location": "L359"}, {"caller_nid": "xpst_state_manager_statemanager_is_circuit_breaker_open", "callee": "get", "is_member_call": true, "source_file": "~/xPST/src/xpst/state_manager.py", "source_location": "L365"}, {"caller_nid": "xpst_state_manager_statemanager_is_circuit_breaker_open", "callee": "get", "is_member_call": true, "source_file": "~/xPST/src/xpst/state_manager.py", "source_location": "L366"}, {"caller_nid": "xpst_state_manager_statemanager_get_statistics", "callee": "get", "is_member_call": true, "source_file": "~/xPST/src/xpst/state_manager.py", "source_location": "L377"}, {"caller_nid": "xpst_state_manager_statemanager_get_statistics", "callee": "values", "is_member_call": true, "source_file": "~/xPST/src/xpst/state_manager.py", "source_location": "L380"}, {"caller_nid": "xpst_state_manager_statemanager_get_statistics", "callee": "get", "is_member_call": true, "source_file": "~/xPST/src/xpst/state_manager.py", "source_location": "L381"}, {"caller_nid": "xpst_state_manager_statemanager_get_statistics", "callee": "items", "is_member_call": true, "source_file": "~/xPST/src/xpst/state_manager.py", "source_location": "L391"}, {"caller_nid": "xpst_state_manager_statemanager_get_statistics", "callee": "get", "is_member_call": true, "source_file": "~/xPST/src/xpst/state_manager.py", "source_location": "L393"}, {"caller_nid": "xpst_state_manager_statemanager_get_statistics", "callee": "get", "is_member_call": true, "source_file": "~/xPST/src/xpst/state_manager.py", "source_location": "L394"}, {"caller_nid": "xpst_state_manager_statemanager_get_statistics", "callee": "get", "is_member_call": true, "source_file": "~/xPST/src/xpst/state_manager.py", "source_location": "L395"}, {"caller_nid": "xpst_state_manager_statemanager_get_statistics", "callee": "get", "is_member_call": true, "source_file": "~/xPST/src/xpst/state_manager.py", "source_location": "L399"}, {"caller_nid": "xpst_state_manager_statemanager_get_statistics", "callee": "get", "is_member_call": true, "source_file": "~/xPST/src/xpst/state_manager.py", "source_location": "L404"}, {"caller_nid": "xpst_state_manager_statemanager_get_statistics", "callee": "get", "is_member_call": true, "source_file": "~/xPST/src/xpst/state_manager.py", "source_location": "L405"}, {"caller_nid": "xpst_state_manager_statemanager_reload", "callee": "load_fresh", "is_member_call": true, "source_file": "~/xPST/src/xpst/state_manager.py", "source_location": "L418"}, {"caller_nid": "xpst_state_manager_statemanager_get_video", "callee": "get", "is_member_call": true, "source_file": "~/xPST/src/xpst/state_manager.py", "source_location": "L424"}, {"caller_nid": "xpst_state_manager_statemanager_list_video_ids", "callee": "keys", "is_member_call": true, "source_file": "~/xPST/src/xpst/state_manager.py", "source_location": "L428"}]}